Workbook

Sheet Urban_threads_original_data
A1: Order ID | B1: Order Date | C1: Customer ID | D1: Type | E1: SKU | F1: Category | G1: Product Name | H1: Unit Price | I1: Qty | J1: Total | K1: Discount Code | L1: Disc % | M1: Payment | N1: Source | O1: City | P1: State | Q1: Warehouse | R1: Del Date | S1: Status | T1: Return? | U1: Reason | V1: Ret Rec | W1: Refund
A2: UT-100001 | B2: 01-10-2024 | C2: CUST_10001 | D2: New | E2: TOP-CAS-M | F2: Tops | G2: Classic Cotton Tee | H2: 1299 | I2: 2 | J2: 2598 | L2: 0 | M2: UPI | N2: Website | O2: Mumbai | P2: Maharashtra | Q2: Mumbai | R2: 05-10-2024 | S2: Delivered | T2: No | W2: Not Applicable
A3: UT-100002 | B3: 01-10-2024 | C3: CUST_10002 | D3: Returning | E3: DRS-FRM-S | F3: Dresses | G3: Floral Midi Dress | H3: 2499 | I3: 1 | J3: 2499 | K3: DIWALI20 | L3: 20 | M3: Credit Card | N3: Mobile App | O3: Delhi | P3: Delhi | Q3: Delhi | R3: 04-10-2024 | S3: Delivered | T3: Yes | U3: Size Issue | V3: 15-10-2024 | W3: Processed
A4: UT-100003 | B4: 10-01-2024 | C4: CUST_10003 | D4: new | E4: BOT-JNS-L | F4: Bottoms | G4: Slim Fit Jeans | H4: 1899 | I4: 1 | J4: 1899 | L4: 0 | M4: COD | N4: Website | O4: Bangalore | P4: Karnataka | Q4: Bangalore | R4: 06-10-2024 | S4: Delivered | T4: No | W4: Not Applicable
A5: UT-100004 | B5: 01-10-2024 | C5: CUST_10004 | D5: New | E5: OUT-JKT-XL | F5: Outerwear | G5: Denim Jacket | H5: 3499 | I5: 1 | J5: 3499 | K5: FIRST15 | L5: 15 | M5: Debit Card | N5: Instagram Shop | O5: Chennai | P5: Tamil Nadu | Q5: Mumbai | R5: 08-10-2024 | S5: Delivered | T5: Yes | U5: Quality Defect | V5: 20-10-2024 | W5: Processed
A6: UT-100005 | B6: 01-10-2024 | C6: CUST_10001 | D6: New | E6: ACC-SCF-OS | F6: Accessories | G6: Silk Scarf | H6: 799 | I6: 3 | J6: 2397 | L6: 0 | M6: UPI | N6: Website | O6: Mumbai | P6: Maharashtra | Q6: Mumbai | R6: 06-10-2024 | S6: Delivered | T6: No | W6: Not Applicable
A7: UT-100006 | B7: 02-10-2024 | C7: CUST_10005 | D7: Returning | E7: TOP-FRM-S | F7: Tops | G7: Printed Blouse | H7: 1599 | I7: 2 | J7: 3198 | L7: 0 | M7: Credit Card | N7: Mobile App | O7: Hyderabad | P7: Telangana | Q7: Bangalore | R7: 07-10-2024 | S7: Delivered | T7: Yes | U7: Changed Mind | V7: 18-10-2024 | W7: Processed
A8: UT-100007 | B8: 02-10-2024 | C8: CUST_10006 | D8: New | E8: DRS-CAS-M | F8: Dresses | G8: A-Line Dress | H8: 2199 | I8: 1 | J8: 2199 | K8: DIWALI20 | L8: 20 | M8: COD | N8: Website | O8: Pune | P8: Maharashtra | Q8: Mumbai | S8: Cancelled | T8: No | W8: Not Applicable
A9: UT-100008 | B9: 02-10-2024 | C9: CUST_10007 | D9: New | E9: BOT-TRS-L | F9: Bottoms | G9: Formal Trousers | H9: 2299 | I9: 1 | J9: 2299 | L9: 0 | M9: UPI | N9: Mobile App | O9: Kolkata | P9: West Bengal | Q9: Delhi | R9: 10-10-2024 | S9: Delivered | T9: No | W9: Not Applicable
A10: UT-100009 | B10: 02-10-2024 | C10: CUST_10008 | D10: Returning | E10: TOP-CAS-XL | F10: Tops | G10: Oversized Tee | H10: 1399 | I10: 5 | J10: 6995 | L10: 0 | M10: Credit Card | N10: Website | O10: Ahmedabad | P10: Gujarat | Q10: Mumbai | R10: 09-10-2024 | S10: Delivered | T10: Yes | U10: Size Issue | V10: 22-10-2024 | W10: Processed
A11: UT-100010 | B11: 02-10-2024 | C11: CUST_10009 | D11: New | E11: OUT-BLZ-M | F11: Outerwear | G11: Casual Blazer | H11: 4999 | I11: -1 | J11: 4999 | L11: 0 | M11: Debit Card | N11: Instagram Shop | O11: Jaipur | P11: Rajasthan | Q11: Delhi | R11: 11-10-2024 | S11: Delivered | T11: Yes | U11: Wrong Item | V11: 25-10-2024 | W11: Pending
A12: UT-100011 | B12: 03-10-2024 | C12: CUST_10010 | D12: New | E12: ACC-BAG-OS | F12: Accessories | G12: Tote Bag | H12: 1299 | I12: 2 | J12: 2598 | K12: FLAT10 | L12: 10 | M12: Wallet | N12: Website | O12: Lucknow | P12: Uttar Pradesh | Q12: Delhi | R12: 10-10-2024 | S12: Delivered | T12: No | W12: Not Applicable
A13: UT-100012 | B13: 03-10-2024 | C13: CUST_10011 | D13: New | E13: DRS-PRT-S | F13: Dresses | G13: Party Dress | H13: 3299 | I13: 1 | J13: 3299 | L13: 0 | M13: COD | N13: Mobile App | O13: Chandigarh | P13: Punjab | Q13: Delhi | S13: RTO | T13: No | W13: Not Applicable
A14: UT-100013 | B14: 03-10-2024 | C14: CUST_10012 | D14: Returning | E14: TOP-SLK-M | F14: Tops | G14: Silk Blouse | H14: 2499 | I14: 1 | J14: 2499 | L14: 0 | M14: Credit Card | N14: Website | O14: Mumbai | P14: Maharashtra | Q14: Mumbai | R14: 09-10-2024 | S14: Delivered | T14: No | W14: Not Applicable
A15: UT-100014 | B15: 03-10-2024 | C15: CUST_10013 | D15: New | E15: BOT-SKT-S | F15: Bottoms | G15: Pleated Skirt | H15: 1799 | I15: 2 | J15: 3598 | K15: DIWALI20 | L15: 20 | M15: UPI | N15: Instagram Shop | O15: Delhi | P15: Delhi | Q15: Delhi | R15: 11-10-2024 | S15: Delivered | T15: Yes | U15: Size Issue | V15: 28-10-2024 | W15: Processed
A16: UT-100015 | B16: 03-10-2024 | C16: CUST_10014 | D16: New | E16: OUT-CRD-L | F16: Outerwear | G16: Knit Cardigan | H16: 2799 | I16: 1 | J16: 2799 | L16: 0 | M16: Debit Card | N16: Mobile App | O16: Bangalore | P16: Karnataka | Q16: Bangalore | R16: 12-10-2024 | S16: Delivered | T16: No | W16: Not Applicable
A17: UT-100016 | B17: 04-10-2024 | C17: CUST_10015 | D17: Returning | E17: ACC-JWL-OS | F17: Accessories | G17: Statement Earrings | H17: 599 | I17: 4 | J17: 2396 | L17: 0 | M17: COD | N17: Website | O17: Noida | P17: Uttar Pradesh | Q17: Delhi | R17: 14-10-2024 | S17: Delivered | T17: Yes | U17: Damaged in Transit | V17: 26-10-2024 | W17: Processed
A18: UT-100017 | B18: 04-10-2024 | C18: CUST_10016 | D18: New | E18: TOP-CRP-XS | F18: Tops | G18: Crop Top | H18: 999 | I18: 1 | J18: 999 | K18: FIRST15 | L18: 15 | M18: UPI | N18: Mobile App | O18: Gurgaon | P18: Haryana | Q18: Delhi | R18: 12-10-2024 | S18: Delievered | T18: No | W18: Not Applicable
A19: UT-100018 | B19: 04-10-2024 | C19: CUST_10017 | D19: New | E19: DRS-MAX-M | F19: Dresses | G19: Maxi Dress | H19: 2899 | I19: 1 | J19: 2899 | L19: 0 | M19: Credit Card | N19: Website | O19: Indore | P19: Madhya Pradesh | Q19: Mumbai | R19: 14-10-2024 | S19: Delivered | T19: No | W19: Not Applicable
A20: UT-100019 | B20: 04-10-2024 | C20: CUST_10018 | D20: Returning | E20: BOT-JGR-M | F20: Bottoms | G20: Joggers | H20: 1499 | I20: 2 | J20: 2998 | L20: 0 | M20: Wallet | N20: Instagram Shop | O20: Surat | P20: Gujarat | Q20: Mumbai | R20: 13-10-2024 | S20: Delivered | T20: Yes | U20: Size Issue | V20: 30-10-2024 | W20: Processed
A21: UT-100020 | B21: 05-10-2024 | C21: CUST_10019 | D21: New | E21: OUT-VST-S | F21: Outerwear | G21: Puffer Vest | H21: 3999 | I21: 1 | J21: 3999 | K21: DIWALI20 | L21: 20 | M21: COD | N21: Website | O21: Patna | P21: Bihar | Q21: Delhi | S21: RTO | T21: No | W21: Not Applicable
A22: UT-100021 | B22: 05-10-2024 | C22: CUST_10020 | D22: New | E22: TOP-TUN-L | F22: Tops | G22: Tunic Top | H22: 1699 | I22: 1 | J22: 1699 | L22: 0 | M22: UPI | N22: Mobile App | O22: Bhopal | P22: Madhya Pradesh | Q22: Mumbai | R22: 15-10-2024 | S22: Delivered | T22: No | W22: Not Applicable
A23: UT-100022 | B23: 05-10-2024 | C23: CUST_10021 | D23: Returning | E23: DRS-SHT-XS | F23: Dresses | G23: Shirt Dress | H23: 2399 | I23: 1 | J23: 2399 | L23: 0 | M23: Credit Card | N23: Website | O23: Nagpur | P23: Maharashtra | Q23: Mumbai | R23: 16-10-2024 | S23: Delivered | T23: Yes | U23: Quality Defect | V23: 02-11-2024 | W23: Processed
A24: UT-100023 | B24: 05-10-2024 | C24: CUST_10022 | D24: New | E24: ACC-BLT-M | F24: Accessories | G24: Leather Belt | H24: 899 | I24: 1 | J24: 899 | K24: FLAT10 | L24: 10 | M24: Debit Card | N24: Mobile App | O24: Coimbatore | P24: Tamil Nadu | Q24: Bangalore | R24: 17-10-2024 | S24: Delivered | T24: No | W24: Not Applicable
A25: UT-100024 | B25: 06-10-2024 | C25: CUST_10023 | D25: New | E25: BOT-SHT-M | F25: Bottoms | G25: Cotton Shorts | H25: 1199 | I25: 3 | J25: 3597 | L25: 0 | M25: COD | N25: Instagram Shop | O25: Kochi | P25: Kerala | Q25: Bangalore | R25: 18-10-2024 | S25: Delivered | T25: Yes | U25: Changed Mind | V25: 05-11-2024 | W25: Processed
A26: UT-100025 | B26: 06-10-2024 | C26: CUST_10024 | D26: New | E26: TOP-PLO-L | F26: Tops | G26: Polo Shirt | H26: 1799 | I26: 2 | J26: 3598 | L26: 0 | M26: UPI | N26: Website | O26: Vizag | P26: Andhra Pradesh | Q26: Bangalore | R26: 17-10-2024 | S26: Delivered | T26: No | W26: Not Applicable
A27: UT-100026 | B27: 06-10-2024 | C27: CUST_10025 | D27: New | E27: DRS-WRK-M | F27: Dresses | G27: Work Dress | H27: 2699 | I27: 1 | J27: 2699 | L27: 0 | M27: Credit Card | N27: Mobile App | O27: Thiruvananthapuram | P27: Kerala | Q27: Bangalore | R27: 18-10-2024 | S27: Delivered | T27: No | W27: Not Applicable
A28: UT-100027 | B28: 06-10-2024 | C28: CUST_10026 | D28: Returning | E28: OUT-TRN-L | F28: Outerwear | G28: Trench Coat | H28: 4599 | I28: 1 | J28: 4599 | K28: FLAT10 | L28: 10 | M28: Debit Card | N28: Website | O28: Mysore | P28: Karnataka | Q28: Bangalore | R28: 19-10-2024 | S28: Delivered | T28: Yes | U28: Size Issue | V28: 08-11-2024 | W28: Processed
A29: UT-100028 | B29: 07-10-2024 | C29: CUST_10027 | D29: New | E29: ACC-HAT-OS | F29: Accessories | G29: Fedora Hat | H29: 1099 | I29: 1 | J29: 1099 | L29: 0 | M29: UPI | N29: Instagram Shop | O29: Vadodara | P29: Gujarat | Q29: Mumbai | R29: 20-10-2024 | S29: Delivered | T29: No | W29: Not Applicable
A30: UT-100029 | B30: 07-10-2024 | C30: CUST_10028 | D30: New | E30: TOP-DNM-M | F30: Tops | G30: Denim Shirt | H30: 1899 | I30: 1 | J30: 1899 | L30: 0 | M30: COD | N30: Mobile App | O30: Rajkot | P30: Gujarat | Q30: Mumbai | S30: RTO | T30: No | W30: Not Applicable
A31: UT-100030 | B31: 07-10-2024 | C31: CUST_10029 | D31: New | E31: BOT-CRG-L | F31: Bottoms | G31: Cargo Pants | H31: 2199 | I31: 1 | J31: 2199 | K31: DIWALI20 | L31: 20 | M31: Credit Card | N31: Website | O31: Kanpur | P31: Uttar Pradesh | Q31: Delhi | R31: 20-10-2024 | S31: Delivered | T31: No | W31: Not Applicable
A32: UT-100031 | B32: 07-10-2024 | C32: CUST_10030 | D32: Returning | E32: DRS-EVE-S | F32: Dresses | G32: Evening Gown | H32: 5499 | I32: 1 | J32: 5499 | L32: 0 | M32: Credit Card | N32: Mobile App | O32: Mumbai | P32: Maharashtra | Q32: Mumbai | R32: 21-10-2024 | S32: Delivered | T32: Yes | U32: Size Issue | V32: 10-11-2024 | W32: Processed
A33: UT-100032 | B33: 08-10-2024 | C33: CUST_10031 | D33: New | E33: TOP-BAS-M | F33: Tops | G33: Basic Tank | H33: 899 | I33: 2 | J33: 1798 | L33: 0 | M33: UPI | N33: Website | O33: Delhi | P33: Delhi | Q33: Delhi | R33: 14-10-2024 | S33: Delivered | T33: No | W33: Not Applicable
A34: UT-100033 | B34: 08-10-2024 | C34: CUST_10032 | D34: New | E34: OUT-WOL-L | F34: Outerwear | G34: Wool Coat | H34: 6999 | I34: 1 | J34: 6999 | K34: FIRST15 | L34: 15 | M34: Debit Card | N34: Instagram Shop | O34: Kolkata | P34: West Bengal | Q34: Delhi | R34: 16-10-2024 | S34: Delivered | T34: Yes | U34: Quality Defect | V34: 05-11-2024 | W34: Processed
A35: UT-100034 | B35: 08-10-2024 | C35: CUST_10033 | D35: Returning | E35: ACC-WCH-OS | F35: Accessories | G35: Fashion Watch | H35: 2999 | I35: 1 | J35: 2999 | L35: 0 | M35: Credit Card | N35: Mobile App | O35: Chennai | P35: Tamil Nadu | Q35: Bangalore | R35: 15-10-2024 | S35: Delivered | T35: No | W35: Not Applicable
A36: UT-100035 | B36: 08-10-2024 | C36: CUST_10034 | D36: New | E36: BOT-DNM-S | F36: Bottoms | G36: Denim Shorts | H36: 1599 | I36: 1 | J36: 1599 | L36: 0 | M36: COD | N36: Website | O36: Hyderabad | P36: Telangana | Q36: Bangalore | R36: 17-10-2024 | S36: Delivered | T36: Yes | U36: Size Issue | V36: 08-11-2024 | W36: Processed
A37: UT-100036 | B37: 09-10-2024 | C37: CUST_10035 | D37: New | E37: DRS-SUN-M | F37: Dresses | G37: Sundress | H37: 1999 | I37: 1 | J37: 1999 | K37: DIWALI20 | L37: 20 | M37: Wallet | N37: Mobile App | O37: Pune | P37: Maharashtra | Q37: Mumbai | R37: 16-10-2024 | S37: Delivered | T37: No | W37: Not Applicable
A38: UT-100037 | B38: 09-10-2024 | C38: CUST_10036 | D38: New | E38: TOP-RFL-S | F38: Tops | G38: Ruffle Top | H38: 1799 | I38: 1 | J38: 1799 | L38: 0 | M38: UPI | N38: Instagram Shop | O38: Ahmedabad | P38: Gujarat | Q38: Mumbai | R38: 17-10-2024 | S38: Delivered | T38: Yes | U38: Changed Mind | V38: 12-11-2024 | W38: Processed
A39: UT-100038 | B39: 09-10-2024 | C39: CUST_10037 | D39: Returning | E39: OUT-LTH-M | F39: Outerwear | G39: Leather Jacket | H39: 7999 | I39: 1 | J39: 7999 | L39: 0 | M39: Credit Card | N39: Website | O39: Jaipur | P39: Rajasthan | Q39: Delhi | R39: 18-10-2024 | S39: Delivered | T39: No | W39: Not Applicable
A40: UT-100039 | B40: 09-10-2024 | C40: CUST_10038 | D40: New | E40: ACC-SNG-OS | F40: Accessories | G40: Sunglasses | H40: 1499 | I40: 1 | J40: 1499 | K40: FLAT10 | L40: 10 | M40: Debit Card | N40: Mobile App | O40: Lucknow | P40: Uttar Pradesh | Q40: Delhi | R40: 17-10-2024 | S40: Delivered | T40: No | W40: Not Applicable
A41: UT-100040 | B41: 10-10-2024 | C41: CUST_10039 | D41: New | E41: BOT-PLZ-L | F41: Bottoms | G41: Palazzo Pants | H41: 1699 | I41: 1 | J41: 1699 | L41: 0 | M41: COD | N41: Website | O41: Bangalore | P41: Karnataka | Q41: Bangalore | R41: 19-10-2024 | S41: Delivered | T41: Yes | U41: Size Issue | V41: 10-11-2024 | W41: Processed
A42: UT-100041 | B42: 10-10-2024 | C42: CUST_10040 | D42: New | E42: DRS-BDC-S | F42: Dresses | G42: Bodycon Dress | H42: 2299 | I42: 1 | J42: 2299 | L42: 0 | M42: UPI | N42: Instagram Shop | O42: Mumbai | P42: Maharashtra | Q42: Mumbai | R42: 18-10-2024 | S42: Delivered | T42: No | W42: Not Applicable
A43: UT-100042 | B43: 10-10-2024 | C43: CUST_10041 | D43: Returning | E43: TOP-OFF-M | F43: Tops | G43: Off-Shoulder Top | H43: 1599 | I43: 2 | J43: 3198 | K43: DIWALI20 | L43: 20 | M43: Credit Card | N43: Mobile App | O43: Delhi | P43: Delhi | Q43: Delhi | R43: 17-10-2024 | S43: Delivered | T43: Yes | U43: Wrong Item | V43: 08-11-2024 | W43: Processed
A44: UT-100043 | B44: 10-10-2024 | C44: CUST_10042 | D44: New | E44: OUT-DNM-L | F44: Outerwear | G44: Denim Vest | H44: 2499 | I44: 1 | J44: 2499 | L44: 0 | M44: Wallet | N44: Website | O44: Chandigarh | P44: Punjab | Q44: Delhi | R44: 20-10-2024 | S44: Delivered | T44: No | W44: Not Applicable
A45: UT-100044 | B45: 11-10-2024 | C45: CUST_10043 | D45: New | E45: ACC-HBG-OS | F45: Accessories | G45: Hobo Bag | H45: 1899 | I45: 1 | J45: 1899 | L45: 0 | M45: Debit Card | N45: Instagram Shop | O45: Noida | P45: Uttar Pradesh | Q45: Delhi | R45: 21-10-2024 | S45: Delivered | T45: Yes | U45: Damaged in Transit | V45: 12-11-2024 | W45: Processed
A46: UT-100045 | B46: 11-10-2024 | C46: CUST_10044 | D46: New | E46: BOT-CHP-M | F46: Bottoms | G46: Chino Pants | H46: 1999 | I46: 1 | J46: 1999 | K46: FIRST15 | L46: 15 | M46: UPI | N46: Mobile App | O46: Gurgaon | P46: Haryana | Q46: Delhi | R46: 19-10-2024 | S46: Delivered | T46: No | W46: Not Applicable
A47: UT-100046 | B47: 11-10-2024 | C47: CUST_10045 | D47: Returning | E47: DRS-WRP-M | F47: Dresses | G47: Wrap Dress | H47: 2599 | I47: 1 | J47: 2599 | L47: 0 | M47: Credit Card | N47: Website | O47: Indore | P47: Madhya Pradesh | Q47: Mumbai | R47: 20-10-2024 | S47: Delivered | T47: No | W47: Not Applicable
A48: UT-100047 | B48: 11-10-2024 | C48: CUST_10046 | D48: New | E48: TOP-STR-S | F48: Tops | G48: Striped Tee | H48: 1299 | I48: 1 | J48: 1299 | L48: 0 | M48: COD | N48: Instagram Shop | O48: Surat | P48: Gujarat | Q48: Mumbai | S48: RTO | T48: No | W48: Not Applicable
A49: UT-100048 | B49: 12-10-2024 | C49: CUST_10047 | D49: New | E49: OUT-PRK-XL | F49: Outerwear | G49: Parka Jacket | H49: 5999 | I49: 1 | J49: 5999 | K49: DIWALI20 | L49: 20 | M49: Credit Card | N49: Mobile App | O49: Patna | P49: Bihar | Q49: Delhi | R49: 22-10-2024 | S49: Delivered | T49: Yes | U49: Size Issue | V49: 15-11-2024 | W49: Processed
A50: UT-100049 | B50: 12-10-2024 | C50: CUST_10048 | D50: New | E50: ACC-EAR-OS | F50: Accessories | G50: Hoop Earrings | H50: 799 | I50: 2 | J50: 1598 | L50: 0 | M50: UPI | N50: Website | O50: Bhopal | P50: Madhya Pradesh | Q50: Mumbai | R50: 20-10-2024 | S50: Delivered | T50: No | W50: Not Applicable
A51: UT-100050 | B51: 12-10-2024 | C51: CUST_10049 | D51: Returning | E51: BOT-LGN-S | F51: Bottoms | G51: Leggings | H51: 999 | I51: 2 | J51: 1998 | L51: 0 | M51: Wallet | N51: Mobile App | O51: Nagpur | P51: Maharashtra | Q51: Mumbai | R51: 19-10-2024 | S51: Delivered | T51: No | W51: Not Applicable
A52: UT-100051 | B52: 12-10-2024 | C52: CUST_10050 | D52: New | E52: DRS-CTN-L | F52: Dresses | G52: Cotton Dress | H52: 1899 | I52: 1 | J52: 1899 | L52: 0 | M52: Debit Card | N52: Instagram Shop | O52: Coimbatore | P52: Tamil Nadu | Q52: Bangalore | R52: 22-10-2024 | S52: Delivered | T52: Yes | U52: Quality Defect | V52: 14-11-2024 | W52: Processed
A53: UT-100052 | B53: 13-10-2024 | C53: CUST_10051 | D53: New | E53: TOP-LCE-M | F53: Tops | G53: Lace Top | H53: 1699 | I53: 1 | J53: 1699 | K53: FLAT10 | L53: 10 | M53: Credit Card | N53: Website | O53: Kochi | P53: Kerala | Q53: Bangalore | R53: 21-10-2024 | S53: Delivered | T53: No | W53: Not Applicable
A54: UT-100053 | B54: 13-10-2024 | C54: CUST_10052 | D54: New | E54: OUT-BOM-M | F54: Outerwear | G54: Bomber Jacket | H54: 3799 | I54: 1 | J54: 3799 | L54: 0 | M54: UPI | N54: Mobile App | O54: Vizag | P54: Andhra Pradesh | Q54: Bangalore | R54: 23-10-2024 | S54: Delivered | T54: Yes | U54: Size Issue | V54: 18-11-2024 | W54: Processed
A55: UT-100054 | B55: 13-10-2024 | C55: CUST_10053 | D55: Returning | E55: ACC-NCK-OS | F55: Accessories | G55: Pendant Necklace | H55: 1299 | I55: 1 | J55: 1299 | L55: 0 | M55: COD | N55: Instagram Shop | O55: Thiruvananthapuram | P55: Kerala | Q55: Bangalore | R55: 22-10-2024 | S55: Delivered | T55: No | W55: Not Applicable
A56: UT-100055 | B56: 13-10-2024 | C56: CUST_10054 | D56: New | E56: BOT-WID-M | F56: Bottoms | G56: Wide Leg Pants | H56: 2099 | I56: 1 | J56: 2099 | K56: DIWALI20 | L56: 20 | M56: Credit Card | N56: Website | O56: Mysore | P56: Karnataka | Q56: Bangalore | R56: 24-10-2024 | S56: Delivered | T56: No | W56: Not Applicable
A57: UT-100056 | B57: 14-10-2024 | C57: CUST_10055 | D57: New | E57: DRS-TIR-S | F57: Dresses | G57: Tiered Dress | H57: 2799 | I57: 1 | J57: 2799 | L57: 0 | M57: Debit Card | N57: Mobile App | O57: Vadodara | P57: Gujarat | Q57: Mumbai | R57: 23-10-2024 | S57: Delivered | T57: Yes | U57: Changed Mind | V57: 16-11-2024 | W57: Processed
A58: UT-100057 | B58: 14-10-2024 | C58: CUST_10056 | D58: New | E58: TOP-PEP-M | F58: Tops | G58: Peplum Top | H58: 1499 | I58: 1 | J58: 1499 | L58: 0 | M58: Wallet | N58: Website | O58: Rajkot | P58: Gujarat | Q58: Mumbai | R58: 22-10-2024 | S58: Delivered | T58: No | W58: Not Applicable
A59: UT-100058 | B59: 14-10-2024 | C59: CUST_10057 | D59: Returning | E59: OUT-QTD-L | F59: Outerwear | G59: Quilted Jacket | H59: 4499 | I59: 1 | J59: 4499 | K59: FIRST15 | L59: 15 | M59: UPI | N59: Instagram Shop | O59: Kanpur | P59: Uttar Pradesh | Q59: Delhi | R59: 25-10-2024 | S59: Delivered | T59: Yes | U59: Wrong Item | V59: 20-11-2024 | W59: Processed
A60: UT-100059 | B60: 14-10-2024 | C60: CUST_10058 | D60: New | E60: ACC-BRC-OS | F60: Accessories | G60: Charm Bracelet | H60: 899 | I60: 1 | J60: 899 | L60: 0 | M60: Credit Card | N60: Mobile App | O60: Mumbai | P60: Maharashtra | Q60: Mumbai | R60: 23-10-2024 | S60: Delivered | T60: No | W60: Not Applicable
A61: UT-100060 | B61: 15-10-2024 | C61: CUST_10059 | D61: New | E61: BOT-CRP-S | F61: Bottoms | G61: Cropped Pants | H61: 1799 | I61: 1 | J61: 1799 | L61: 0 | M61: COD | N61: Website | O61: Delhi | P61: Delhi | Q61: Delhi | S61: RTO | T61: No | W61: Not Applicable
A62: UT-100061 | B62: 15-10-2024 | C62: CUST_10060 | D62: New | E62: DRS-SLP-M | F62: Dresses | G62: Slip Dress | H62: 2199 | I62: 1 | J62: 2199 | K62: DIWALI20 | L62: 20 | M62: Debit Card | N62: Instagram Shop | O62: Kolkata | P62: West Bengal | Q62: Delhi | R62: 26-10-2024 | S62: Delivered | T62: Yes | U62: Size Issue | V62: 22-11-2024 | W62: Processed
A63: UT-100062 | B63: 15-10-2024 | C63: CUST_10061 | D63: Returning | E63: TOP-HLT-L | F63: Tops | G63: Halter Top | H63: 1399 | I63: 1 | J63: 1399 | L63: 0 | M63: UPI | N63: Mobile App | O63: Chennai | P63: Tamil Nadu | Q63: Bangalore | R63: 24-10-2024 | S63: Delivered | T63: No | W63: Not Applicable
A64: UT-100063 | B64: 15-10-2024 | C64: CUST_10062 | D64: New | E64: OUT-FLC-M | F64: Outerwear | G64: Fleece Jacket | H64: 2999 | I64: 1 | J64: 2999 | L64: 0 | M64: Credit Card | N64: Website | O64: Hyderabad | P64: Telangana | Q64: Bangalore | R64: 27-10-2024 | S64: Delivered | T64: Yes | U64: Quality Defect | V64: 24-11-2024 | W64: Processed
A65: UT-100064 | B65: 16-10-2024 | C65: CUST_10063 | D65: New | E65: ACC-RNG-OS | F65: Accessories | G65: Cocktail Ring | H65: 699 | I65: 2 | J65: 1398 | K65: FLAT10 | L65: 10 | M65: Wallet | N65: Instagram Shop | O65: Pune | P65: Maharashtra | Q65: Mumbai | R65: 25-10-2024 | S65: Delivered | T65: No | W65: Not Applicable
A66: UT-100065 | B66: 16-10-2024 | C66: CUST_10064 | D66: New | E66: BOT-SKN-M | F66: Bottoms | G66: Skinny Jeans | H66: 2199 | I66: 1 | J66: 2199 | L66: 0 | M66: COD | N66: Mobile App | O66: Ahmedabad | P66: Gujarat | Q66: Mumbai | R66: 28-10-2024 | S66: Delivered | T66: Yes | U66: Size Issue | V66: 25-11-2024 | W66: Processed
A67: UT-100066 | B67: 16-10-2024 | C67: CUST_10065 | D67: Returning | E67: DRS-KNT-S | F67: Dresses | G67: Knit Dress | H67: 2499 | I67: 1 | J67: 2499 | L67: 0 | M67: Credit Card | N67: Website | O67: Jaipur | P67: Rajasthan | Q67: Delhi | R67: 26-10-2024 | S67: Delivered | T67: No | W67: Not Applicable
A68: UT-100067 | B68: 16-10-2024 | C68: CUST_10066 | D68: New | E68: TOP-EMB-M | F68: Tops | G68: Embroidered Top | H68: 1899 | I68: 1 | J68: 1899 | K68: DIWALI20 | L68: 20 | M68: UPI | N68: Instagram Shop | O68: Lucknow | P68: Uttar Pradesh | Q68: Delhi | R68: 27-10-2024 | S68: Delivered | T68: Yes | U68: Changed Mind | V68: 20-11-2024 | W68: Processed
A69: UT-100068 | B69: 17-10-2024 | C69: CUST_10067 | D69: New | E69: OUT-SHR-L | F69: Outerwear | G69: Shrug | H69: 1299 | I69: 1 | J69: 1299 | L69: 0 | M69: Debit Card | N69: Mobile App | O69: Bangalore | P69: Karnataka | Q69: Bangalore | R69: 28-10-2024 | S69: Delivered | T69: No | W69: Not Applicable
A70: UT-100069 | B70: 17-10-2024 | C70: CUST_10068 | D70: New | E70: ACC-CLT-OS | F70: Accessories | G70: Clutch Bag | H70: 1599 | I70: 1 | J70: 1599 | L70: 0 | M70: Credit Card | N70: Website | O70: Mumbai | P70: Maharashtra | Q70: Mumbai | R70: 27-10-2024 | S70: Delivered | T70: Yes | U70: Damaged in Transit | V70: 22-11-2024 | W70: Processed
A71: UT-100070 | B71: 17-10-2024 | C71: CUST_10069 | D71: Returning | E71: BOT-FLR-S | F71: Bottoms | G71: Flared Jeans | H71: 2099 | I71: 1 | J71: 2099 | K71: FIRST15 | L71: 15 | M71: UPI | N71: Instagram Shop | O71: Delhi | P71: Delhi | Q71: Delhi | R71: 29-10-2024 | S71: Delivered | T71: No | W71: Not Applicable
A72: UT-100071 | B72: 17-10-2024 | C72: CUST_10070 | D72: New | E72: DRS-PIN-M | F72: Dresses | G72: Pinafore Dress | H72: 2299 | I72: 1 | J72: 2299 | L72: 0 | M72: COD | N72: Mobile App | O72: Chandigarh | P72: Punjab | Q72: Delhi | S72: RTO | T72: No | W72: Not Applicable
A73: UT-100072 | B73: 18-10-2024 | C73: CUST_10071 | D73: New | E73: TOP-CRW-L | F73: Tops | G73: Crew Neck Tee | H73: 1199 | I73: 2 | J73: 2398 | L73: 0 | M73: Wallet | N73: Website | O73: Noida | P73: Uttar Pradesh | Q73: Delhi | R73: 28-10-2024 | S73: Delivered | T73: No | W73: Not Applicable
A74: UT-100073 | B74: 18-10-2024 | C74: CUST_10072 | D74: New | E74: OUT-CDG-M | F74: Outerwear | G74: Cardigan | H74: 2599 | I74: 1 | J74: 2599 | K74: DIWALI20 | L74: 20 | M74: Credit Card | N74: Instagram Shop | O74: Gurgaon | P74: Haryana | Q74: Delhi | R74: 30-10-2024 | S74: Delivered | T74: Yes | U74: Size Issue | V74: 26-11-2024 | W74: Processed
A75: UT-100074 | B75: 18-10-2024 | C75: CUST_10073 | D75: Returning | E75: ACC-SCR-OS | F75: Accessories | G75: Hair Scrunchie | H75: 299 | I75: 5 | J75: 1495 | L75: 0 | M75: UPI | N75: Mobile App | O75: Indore | P75: Madhya Pradesh | Q75: Mumbai | R75: 27-10-2024 | S75: Delivered | T75: No | W75: Not Applicable
A76: UT-100075 | B76: 18-10-2024 | C76: CUST_10074 | D76: New | E76: BOT-PPR-M | F76: Bottoms | G76: Paper Bag Pants | H76: 1899 | I76: 1 | J76: 1899 | L76: 0 | M76: Debit Card | N76: Website | O76: Surat | P76: Gujarat | Q76: Mumbai | R76: 30-10-2024 | S76: Delivered | T76: Yes | U76: Wrong Item | V76: 28-11-2024 | W76: Processed
A77: UT-100076 | B77: 19-10-2024 | C77: CUST_10075 | D77: New | E77: DRS-SMK-S | F77: Dresses | G77: Smocked Dress | H77: 2199 | I77: 1 | J77: 2199 | L77: 0 | M77: Credit Card | N77: Instagram Shop | O77: Patna | P77: Bihar | Q77: Delhi | R77: 31-10-2024 | S77: Delivered | T77: No | W77: Not Applicable
A78: UT-100077 | B78: 19-10-2024 | C78: CUST_10076 | D78: New | E78: TOP-BTN-M | F78: Tops | G78: Button-Down Shirt | H78: 1799 | I78: 1 | J78: 1799 | K78: FLAT10 | L78: 10 | M78: COD | N78: Mobile App | O78: Bhopal | P78: Madhya Pradesh | Q78: Mumbai | R78: 29-10-2024 | S78: Delivered | T78: Yes | U78: Quality Defect | V78: 25-11-2024 | W78: Processed
A79: UT-100078 | B79: 19-10-2024 | C79: CUST_10077 | D79: Returning | E79: OUT-VLV-L | F79: Outerwear | G79: Velvet Blazer | H79: 4999 | I79: 1 | J79: 4999 | L79: 0 | M79: UPI | N79: Website | O79: Nagpur | P79: Maharashtra | Q79: Mumbai | R79: 01-11-2024 | S79: Delivered | T79: No | W79: Not Applicable
A80: UT-100079 | B80: 19-10-2024 | C80: CUST_10078 | D80: New | E80: ACC-TOT-OS | F80: Accessories | G80: Canvas Tote | H80: 999 | I80: 1 | J80: 999 | L80: 0 | M80: Wallet | N80: Instagram Shop | O80: Coimbatore | P80: Tamil Nadu | Q80: Bangalore | R80: 30-10-2024 | S80: Delivered | T80: Yes | U80: Size Issue | V80: 28-11-2024 | W80: Processed
A81: UT-100080 | B81: 20-10-2024 | C81: CUST_10079 | D81: New | E81: BOT-CRG-S | F81: Bottoms | G81: Cargo Shorts | H81: 1499 | I81: 1 | J81: 1499 | K81: DIWALI20 | L81: 20 | M81: Credit Card | N81: Mobile App | O81: Kochi | P81: Kerala | Q81: Bangalore | R81: 31-10-2024 | S81: Delivered | T81: No | W81: Not Applicable
A82: UT-100081 | B82: 20-10-2024 | C82: CUST_10080 | D82: New | E82: DRS-BTR-M | F82: Dresses | G82: Butterfly Dress | H82: 2899 | I82: 1 | J82: 2899 | L82: 0 | M82: Debit Card | N82: Website | O82: Vizag | P82: Andhra Pradesh | Q82: Bangalore | R82: 02-11-2024 | S82: Delivered | T82: Yes | U82: Changed Mind | V82: 30-11-2024 | W82: Processed
A83: UT-100082 | B83: 20-10-2024 | C83: CUST_10081 | D83: Returning | E83: TOP-VNK-L | F83: Tops | G83: V-Neck Tee | H83: 1099 | I83: 2 | J83: 2198 | L83: 0 | M83: UPI | N83: Instagram Shop | O83: Thiruvananthapuram | P83: Kerala | Q83: Bangalore | R83: 30-10-2024 | S83: Delivered | T83: No | W83: Not Applicable
A84: UT-100083 | B84: 20-10-2024 | C84: CUST_10082 | D84: New | E84: OUT-TRN-M | F84: Outerwear | G84: Trench Coat | H84: 5499 | I84: 1 | J84: 5499 | K84: FIRST15 | L84: 15 | M84: Credit Card | N84: Mobile App | O84: Mysore | P84: Karnataka | Q84: Bangalore | R84: 03-11-2024 | S84: Delivered | T84: Yes | U84: Size Issue | V84: 01-12-2024 | W84: Processed
A85: UT-100084 | B85: 21-10-2024 | C85: CUST_10083 | D85: New | E85: ACC-BDY-OS | F85: Accessories | G85: Body Chain | H85: 799 | I85: 1 | J85: 799 | L85: 0 | M85: COD | N85: Website | O85: Vadodara | P85: Gujarat | Q85: Mumbai | S85: RTO | T85: No | W85: Not Applicable
A86: UT-100085 | B86: 21-10-2024 | C86: CUST_10084 | D86: New | E86: BOT-JGR-L | F86: Bottoms | G86: Jogger Pants | H86: 1599 | I86: 1 | J86: 1599 | L86: 0 | M86: Wallet | N86: Instagram Shop | O86: Rajkot | P86: Gujarat | Q86: Mumbai | R86: 02-11-2024 | S86: Delivered | T86: No | W86: Not Applicable
A87: UT-100086 | B87: 21-10-2024 | C87: CUST_10085 | D87: Returning | E87: DRS-RFL-S | F87: Dresses | G87: Ruffle Dress | H87: 2699 | I87: 1 | J87: 2699 | K87: DIWALI20 | L87: 20 | M87: Credit Card | N87: Mobile App | O87: Kanpur | P87: Uttar Pradesh | Q87: Delhi | R87: 01-11-2024 | S87: Delivered | T87: Yes | U87: Quality Defect | V87: 30-11-2024 | W87: Processed
A88: UT-100087 | B88: 21-10-2024 | C88: CUST_10086 | D88: New | E88: TOP-SQR-M | F88: Tops | G88: Square Neck Top | H88: 1499 | I88: 1 | J88: 1499 | L88: 0 | M88: UPI | N88: Website | O88: Mumbai | P88: Maharashtra | Q88: Mumbai | R88: 02-11-2024 | S88: Delivered | T88: No | W88: Not Applicable
A89: UT-100088 | B89: 22-10-2024 | C89: CUST_10087 | D89: New | E89: OUT-WND-L | F89: Outerwear | G89: Windbreaker | H89: 3299 | I89: 1 | J89: 3299 | L89: 0 | M89: Debit Card | N89: Instagram Shop | O89: Delhi | P89: Delhi | Q89: Delhi | R89: 04-11-2024 | S89: Delivered | T89: Yes | U89: Wrong Item | V89: 03-12-2024 | W89: Processed
A90: UT-100089 | B90: 22-10-2024 | C90: CUST_10088 | D90: New | E90: ACC-ANK-OS | F90: Accessories | G90: Anklet | H90: 499 | I90: 2 | J90: 998 | K90: FLAT10 | L90: 10 | M90: Credit Card | N90: Mobile App | O90: Kolkata | P90: West Bengal | Q90: Delhi | R90: 01-11-2024 | S90: Delivered | T90: No | W90: Not Applicable
A91: UT-100090 | B91: 22-10-2024 | C91: CUST_10089 | D91: Returning | E91: BOT-TRS-M | F91: Bottoms | G91: Tailored Trousers | H91: 2399 | I91: 1 | J91: 2399 | L91: 0 | M91: UPI | N91: Website | O91: Chennai | P91: Tamil Nadu | Q91: Bangalore | R91: 03-11-2024 | S91: Delivered | T91: No | W91: Not Applicable
A92: UT-100091 | B92: 22-10-2024 | C92: CUST_10090 | D92: New | E92: DRS-LST-M | F92: Dresses | G92: Lace Trim Dress | H92: 2599 | I92: 1 | J92: 2599 | L92: 0 | M92: COD | N92: Instagram Shop | O92: Hyderabad | P92: Telangana | Q92: Bangalore | S92: RTO | T92: No | W92: Not Applicable
A93: UT-100092 | B93: 23-10-2024 | C93: CUST_10091 | D93: New | E93: TOP-TIE-S | F93: Tops | G93: Tie-Front Top | H93: 1399 | I93: 1 | J93: 1399 | K93: DIWALI20 | L93: 20 | M93: Wallet | N93: Mobile App | O93: Pune | P93: Maharashtra | Q93: Mumbai | R93: 03-11-2024 | S93: Delivered | T93: Yes | U93: Size Issue | V93: 02-12-2024 | W93: Processed
A94: UT-100093 | B94: 23-10-2024 | C94: CUST_10092 | D94: New | E94: OUT-PUF-M | F94: Outerwear | G94: Puffer Jacket | H94: 4299 | I94: 1 | J94: 4299 | L94: 0 | M94: Credit Card | N94: Website | O94: Ahmedabad | P94: Gujarat | Q94: Mumbai | R94: 05-11-2024 | S94: Delivered | T94: No | W94: Not Applicable
A95: UT-100094 | B95: 23-10-2024 | C95: CUST_10093 | D95: Returning | E95: ACC-HDR-OS | F95: Accessories | G95: Hairband | H95: 399 | I95: 3 | J95: 1197 | L95: 0 | M95: UPI | N95: Instagram Shop | O95: Jaipur | P95: Rajasthan | Q95: Delhi | R95: 02-11-2024 | S95: Delivered | T95: No | W95: Not Applicable
A96: UT-100095 | B96: 23-10-2024 | C96: CUST_10094 | D96: New | E96: BOT-PLT-L | F96: Bottoms | G96: Pleated Trousers | H96: 2199 | I96: 1 | J96: 2199 | K96: FIRST15 | L96: 15 | M96: Debit Card | N96: Mobile App | O96: Lucknow | P96: Uttar Pradesh | Q96: Delhi | R96: 05-11-2024 | S96: Delivered | T96: Yes | U96: Damaged in Transit | V96: 05-12-2024 | W96: Processed
A97: UT-100096 | B97: 24-10-2024 | C97: CUST_10095 | D97: New | E97: DRS-SHR-S | F97: Dresses | G97: Shirtdress | H97: 2399 | I97: 1 | J97: 2399 | L97: 0 | M97: Credit Card | N97: Website | O97: Bangalore | P97: Karnataka | Q97: Bangalore | R97: 04-11-2024 | S97: Delivered | T97: No | W97: Not Applicable
A98: UT-100097 | B98: 24-10-2024 | C98: CUST_10096 | D98: New | E98: TOP-GRF-M | F98: Tops | G98: Graphic Tee | H98: 1299 | I98: 1 | J98: 1299 | L98: 0 | M98: COD | N98: Instagram Shop | O98: Mumbai | P98: Maharashtra | Q98: Mumbai | R98: 06-11-2024 | S98: Delivered | T98: Yes | U98: Changed Mind | V98: 05-12-2024 | W98: Processed
A99: UT-100098 | B99: 24-10-2024 | C99: CUST_10097 | D99: Returning | E99: OUT-SHW-L | F99: Outerwear | G99: Shawl Wrap | H99: 2799 | I99: 1 | J99: 2799 | K99: DIWALI20 | L99: 20 | M99: UPI | N99: Mobile App | O99: Delhi | P99: Delhi | Q99: Delhi | R99: 05-11-2024 | S99: Delivered | T99: No | W99: Not Applicable
A100: UT-100099 | B100: 24-10-2024 | C100: CUST_10098 | D100: New | E100: ACC-BLT-S | F100: Accessories | G100: Braided Belt | H100: 699 | I100: 1 | J100: 699 | L100: 0 | M100: Wallet | N100: Website | O100: Chandigarh | P100: Punjab | Q100: Delhi | R100: 04-11-2024 | S100: Delivered | T100: No | W100: Not Applicable
...

Sheet Validated_Raw_Data
A1: Order ID | B1: Order Date | C1: Order_Date_Validation_Q4 | D1: Customer ID | E1: Type | F1: Product_SKU | G1: Category | H1: Product Name | I1: Unit Price | J1: Qty | K1: Order_Quantity_Validation | L1: Total | M1: Order_Total_After_Discount | N1: Discount Code | O1: Disc % | P1: Discount_Amount | Q1: Payment | R1: Source | S1: City | T1: State | U1: Warehouse | V1: Delivery Date | W1: Delivery_Date_Validation | X1: Delivery_Time_Validation | Y1: Status | Z1: Return? | AA1: Reason | AB1: Return Received | AC1: Return_Date_Validation | AD1: Return_Window_Validation | AE1: Refund
A2: UT-100001 | B2: 45566 | C2: Valid Q4 | D2: CUST_10001 | E2: New | F2: TOP-CAS-M | G2: Tops | H2: Classic Cotton Tee | I2: 1299 | J2: 2 | K2: Valid Quantity | L2: 2598 | M2: 2598 | O2: 0 | P2: 0 | Q2: UPI | R2: Website | S2: Mumbai | T2: Maharashtra | U2: Mumbai | V2: 45570 | W2: Valid Date | X2: On time delivery | Y2: Delivered | Z2: No | AC2: Not Returned | AD2: Not returned | AE2: Not Applicable
A3: UT-100002 | B3: 45566 | C3: Valid Q4 | D3: CUST_10002 | E3: Returning | F3: DRS-FRM-S | G3: Dresses | H3: Floral Midi Dress | I3: 2499 | J3: 1 | K3: Valid Quantity | L3: 2499 | M3: 1999.2 | N3: DIWALI20 | O3: 20 | P3: 499.8 | Q3: Credit Card | R3: Mobile App | S3: Delhi | T3: Delhi | U3: Delhi | V3: 45569 | W3: Valid Date | X3: On time delivery | Y3: Delivered | Z3: Yes | AA3: Size Issue | AB3: 45580 | AC3: Returned | AD3: Valid | AE3: Processed
A4: UT-100003 | B4: 45301 | C4: Out of Q4 | D4: CUST_10003 | E4: New | F4: BOT-JNS-L | G4: Bottoms | H4: Slim Fit Jeans | I4: 1899 | J4: 1 | K4: Valid Quantity | L4: 1899 | M4: 1899 | O4: 0 | P4: 0 | Q4: COD | R4: Website | S4: Bangalore | T4: Karnataka | U4: Bangalore | V4: 45571 | W4: Valid Date | X4: Late delivery | Y4: Delivered | Z4: No | AC4: Not Returned | AD4: Not returned | AE4: Not Applicable
A5: UT-100004 | B5: 45566 | C5: Valid Q4 | D5: CUST_10004 | E5: New | F5: OUT-JKT-XL | G5: Outerwear | H5: Denim Jacket | I5: 3499 | J5: 1 | K5: Valid Quantity | L5: 3499 | M5: 2974.15 | N5: FIRST15 | O5: 15 | P5: 524.85 | Q5: Debit Card | R5: Instagram Shop | S5: Chennai | T5: Tamil Nadu | U5: Mumbai | V5: 45573 | W5: Valid Date | X5: On time delivery | Y5: Delivered | Z5: Yes | AA5: Quality Defect | AB5: 45585 | AC5: Returned | AD5: Valid | AE5: Processed
A6: UT-100005 | B6: 45566 | C6: Valid Q4 | D6: CUST_10001 | E6: New | F6: ACC-SCF-OS | G6: Accessories | H6: Silk Scarf | I6: 799 | J6: 3 | K6: Valid Quantity | L6: 2397 | M6: 2397 | O6: 0 | P6: 0 | Q6: UPI | R6: Website | S6: Mumbai | T6: Maharashtra | U6: Mumbai | V6: 45571 | W6: Valid Date | X6: On time delivery | Y6: Delivered | Z6: No | AC6: Not Returned | AD6: Not returned | AE6: Not Applicable
A7: UT-100006 | B7: 45567 | C7: Valid Q4 | D7: CUST_10005 | E7: Returning | F7: TOP-FRM-S | G7: Tops | H7: Printed Blouse | I7: 1599 | J7: 2 | K7: Valid Quantity | L7: 3198 | M7: 3198 | O7: 0 | P7: 0 | Q7: Credit Card | R7: Mobile App | S7: Hyderabad | T7: Telangana | U7: Bangalore | V7: 45572 | W7: Valid Date | X7: On time delivery | Y7: Delivered | Z7: Yes | AA7: Changed Mind | AB7: 45583 | AC7: Returned | AD7: Valid | AE7: Processed
A8: UT-100007 | B8: 45567 | C8: Valid Q4 | D8: CUST_10006 | E8: New | F8: DRS-CAS-M | G8: Dresses | H8: A-Line Dress | I8: 2199 | J8: 1 | K8: Valid Quantity | L8: 2199 | M8: 1759.2 | N8: DIWALI20 | O8: 20 | P8: 439.8 | Q8: COD | R8: Website | S8: Pune | T8: Maharashtra | U8: Mumbai | W8: Not Delivered | X8: Not delivered | Y8: Cancelled | Z8: No | AC8: Not Delivered | AD8: Not returned | AE8: Not Applicable
A9: UT-100008 | B9: 45567 | C9: Valid Q4 | D9: CUST_10007 | E9: New | F9: BOT-TRS-L | G9: Bottoms | H9: Formal Trousers | I9: 2299 | J9: 1 | K9: Valid Quantity | L9: 2299 | M9: 2299 | O9: 0 | P9: 0 | Q9: UPI | R9: Mobile App | S9: Kolkata | T9: West Bengal | U9: Delhi | V9: 45575 | W9: Valid Date | X9: On time delivery | Y9: Delivered | Z9: No | AC9: Not Returned | AD9: Not returned | AE9: Not Applicable
A10: UT-100009 | B10: 45567 | C10: Valid Q4 | D10: CUST_10008 | E10: Returning | F10: TOP-CAS-XL | G10: Tops | H10: Oversized Tee | I10: 1399 | J10: 5 | K10: Valid Quantity | L10: 6995 | M10: 6995 | O10: 0 | P10: 0 | Q10: Credit Card | R10: Website | S10: Ahmedabad | T10: Gujarat | U10: Mumbai | V10: 45574 | W10: Valid Date | X10: On time delivery | Y10: Delivered | Z10: Yes | AA10: Size Issue | AB10: 45587 | AC10: Returned | AD10: Valid | AE10: Processed
A11: UT-100010 | B11: 45567 | C11: Valid Q4 | D11: CUST_10009 | E11: New | F11: OUT-BLZ-M | G11: Outerwear | H11: Casual Blazer | I11: 4999 | J11: -1 | K11: Invalid Quantity | L11: 4999 | M11: -4999 | O11: 0 | P11: 0 | Q11: Debit Card | R11: Instagram Shop | S11: Jaipur | T11: Rajasthan | U11: Delhi | V11: 45576 | W11: Valid Date | X11: On time delivery | Y11: Delivered | Z11: Yes | AA11: Wrong Item | AB11: 45590 | AC11: Returned | AD11: Valid | AE11: Pending
A12: UT-100011 | B12: 45568 | C12: Valid Q4 | D12: CUST_10010 | E12: New | F12: ACC-BAG-OS | G12: Accessories | H12: Tote Bag | I12: 1299 | J12: 2 | K12: Valid Quantity | L12: 2598 | M12: 2338.2 | N12: FLAT10 | O12: 10 | P12: 259.8 | Q12: Wallet | R12: Website | S12: Lucknow | T12: Uttar Pradesh | U12: Delhi | V12: 45575 | W12: Valid Date | X12: On time delivery | Y12: Delivered | Z12: No | AC12: Not Returned | AD12: Not returned | AE12: Not Applicable
A13: UT-100012 | B13: 45568 | C13: Valid Q4 | D13: CUST_10011 | E13: New | F13: DRS-PRT-S | G13: Dresses | H13: Party Dress | I13: 3299 | J13: 1 | K13: Valid Quantity | L13: 3299 | M13: 3299 | O13: 0 | P13: 0 | Q13: COD | R13: Mobile App | S13: Chandigarh | T13: Punjab | U13: Delhi | W13: Not Delivered | X13: Not delivered | Y13: RTO | Z13: No | AC13: Not Delivered | AD13: Not returned | AE13: Not Applicable
A14: UT-100013 | B14: 45568 | C14: Valid Q4 | D14: CUST_10012 | E14: Returning | F14: TOP-SLK-M | G14: Tops | H14: Silk Blouse | I14: 2499 | J14: 1 | K14: Valid Quantity | L14: 2499 | M14: 2499 | O14: 0 | P14: 0 | Q14: Credit Card | R14: Website | S14: Mumbai | T14: Maharashtra | U14: Mumbai | V14: 45574 | W14: Valid Date | X14: On time delivery | Y14: Delivered | Z14: No | AC14: Not Returned | AD14: Not returned | AE14: Not Applicable
A15: UT-100014 | B15: 45568 | C15: Valid Q4 | D15: CUST_10013 | E15: New | F15: BOT-SKT-S | G15: Bottoms | H15: Pleated Skirt | I15: 1799 | J15: 2 | K15: Valid Quantity | L15: 3598 | M15: 2878.4 | N15: DIWALI20 | O15: 20 | P15: 719.6 | Q15: UPI | R15: Instagram Shop | S15: Delhi | T15: Delhi | U15: Delhi | V15: 45576 | W15: Valid Date | X15: On time delivery | Y15: Delivered | Z15: Yes | AA15: Size Issue | AB15: 45593 | AC15: Returned | AD15: Valid | AE15: Processed
A16: UT-100015 | B16: 45568 | C16: Valid Q4 | D16: CUST_10014 | E16: New | F16: OUT-CRD-L | G16: Outerwear | H16: Knit Cardigan | I16: 2799 | J16: 1 | K16: Valid Quantity | L16: 2799 | M16: 2799 | O16: 0 | P16: 0 | Q16: Debit Card | R16: Mobile App | S16: Bangalore | T16: Karnataka | U16: Bangalore | V16: 45577 | W16: Valid Date | X16: On time delivery | Y16: Delivered | Z16: No | AC16: Not Returned | AD16: Not returned | AE16: Not Applicable
A17: UT-100016 | B17: 45569 | C17: Valid Q4 | D17: CUST_10015 | E17: Returning | F17: ACC-JWL-OS | G17: Accessories | H17: Statement Earrings | I17: 599 | J17: 4 | K17: Valid Quantity | L17: 2396 | M17: 2396 | O17: 0 | P17: 0 | Q17: COD | R17: Website | S17: Noida | T17: Uttar Pradesh | U17: Delhi | V17: 45579 | W17: Valid Date | X17: On time delivery | Y17: Delivered | Z17: Yes | AA17: Damaged in Transit | AB17: 45591 | AC17: Returned | AD17: Valid | AE17: Processed
A18: UT-100017 | B18: 45569 | C18: Valid Q4 | D18: CUST_10016 | E18: New | F18: TOP-CRP-XS | G18: Tops | H18: Crop Top | I18: 999 | J18: 1 | K18: Valid Quantity | L18: 999 | M18: 849.15 | N18: FIRST15 | O18: 15 | P18: 149.85 | Q18: UPI | R18: Mobile App | S18: Gurgaon | T18: Haryana | U18: Delhi | V18: 45577 | W18: Valid Date | X18: On time delivery | Y18: Delivered | Z18: No | AC18: Not Returned | AD18: Not returned | AE18: Not Applicable
A19: UT-100018 | B19: 45569 | C19: Valid Q4 | D19: CUST_10017 | E19: New | F19: DRS-MAX-M | G19: Dresses | H19: Maxi Dress | I19: 2899 | J19: 1 | K19: Valid Quantity | L19: 2899 | M19: 2899 | O19: 0 | P19: 0 | Q19: Credit Card | R19: Website | S19: Indore | T19: Madhya Pradesh | U19: Mumbai | V19: 45579 | W19: Valid Date | X19: On time delivery | Y19: Delivered | Z19: No | AC19: Not Returned | AD19: Not returned | AE19: Not Applicable
A20: UT-100019 | B20: 45569 | C20: Valid Q4 | D20: CUST_10018 | E20: Returning | F20: BOT-JGR-M | G20: Bottoms | H20: Joggers | I20: 1499 | J20: 2 | K20: Valid Quantity | L20: 2998 | M20: 2998 | O20: 0 | P20: 0 | Q20: Wallet | R20: Instagram Shop | S20: Surat | T20: Gujarat | U20: Mumbai | V20: 45578 | W20: Valid Date | X20: On time delivery | Y20: Delivered | Z20: Yes | AA20: Size Issue | AB20: 45595 | AC20: Returned | AD20: Valid | AE20: Processed
A21: UT-100020 | B21: 45570 | C21: Valid Q4 | D21: CUST_10019 | E21: New | F21: OUT-VST-S | G21: Outerwear | H21: Puffer Vest | I21: 3999 | J21: 1 | K21: Valid Quantity | L21: 3999 | M21: 3199.2 | N21: DIWALI20 | O21: 20 | P21: 799.8 | Q21: COD | R21: Website | S21: Patna | T21: Bihar | U21: Delhi | W21: Not Delivered | X21: Not delivered | Y21: RTO | Z21: No | AC21: Not Delivered | AD21: Not returned | AE21: Not Applicable
A22: UT-100021 | B22: 45570 | C22: Valid Q4 | D22: CUST_10020 | E22: New | F22: TOP-TUN-L | G22: Tops | H22: Tunic Top | I22: 1699 | J22: 1 | K22: Valid Quantity | L22: 1699 | M22: 1699 | O22: 0 | P22: 0 | Q22: UPI | R22: Mobile App | S22: Bhopal | T22: Madhya Pradesh | U22: Mumbai | V22: 45580 | W22: Valid Date | X22: On time delivery | Y22: Delivered | Z22: No | AC22: Not Returned | AD22: Not returned | AE22: Not Applicable
A23: UT-100022 | B23: 45570 | C23: Valid Q4 | D23: CUST_10021 | E23: Returning | F23: DRS-SHT-XS | G23: Dresses | H23: Shirt Dress | I23: 2399 | J23: 1 | K23: Valid Quantity | L23: 2399 | M23: 2399 | O23: 0 | P23: 0 | Q23: Credit Card | R23: Website | S23: Nagpur | T23: Maharashtra | U23: Mumbai | V23: 45581 | W23: Valid Date | X23: On time delivery | Y23: Delivered | Z23: Yes | AA23: Quality Defect | AB23: 45598 | AC23: Returned | AD23: Valid | AE23: Processed
A24: UT-100023 | B24: 45570 | C24: Valid Q4 | D24: CUST_10022 | E24: New | F24: ACC-BLT-M | G24: Accessories | H24: Leather Belt | I24: 899 | J24: 1 | K24: Valid Quantity | L24: 899 | M24: 809.1 | N24: FLAT10 | O24: 10 | P24: 89.9 | Q24: Debit Card | R24: Mobile App | S24: Coimbatore | T24: Tamil Nadu | U24: Bangalore | V24: 45582 | W24: Valid Date | X24: On time delivery | Y24: Delivered | Z24: No | AC24: Not Returned | AD24: Not returned | AE24: Not Applicable
A25: UT-100024 | B25: 45571 | C25: Valid Q4 | D25: CUST_10023 | E25: New | F25: BOT-SHT-M | G25: Bottoms | H25: Cotton Shorts | I25: 1199 | J25: 3 | K25: Valid Quantity | L25: 3597 | M25: 3597 | O25: 0 | P25: 0 | Q25: COD | R25: Instagram Shop | S25: Kochi | T25: Kerala | U25: Bangalore | V25: 45583 | W25: Valid Date | X25: On time delivery | Y25: Delivered | Z25: Yes | AA25: Changed Mind | AB25: 45601 | AC25: Returned | AD25: Valid | AE25: Processed
A26: UT-100025 | B26: 45571 | C26: Valid Q4 | D26: CUST_10024 | E26: New | F26: TOP-PLO-L | G26: Tops | H26: Polo Shirt | I26: 1799 | J26: 2 | K26: Valid Quantity | L26: 3598 | M26: 3598 | O26: 0 | P26: 0 | Q26: UPI | R26: Website | S26: Vizag | T26: Andhra Pradesh | U26: Bangalore | V26: 45582 | W26: Valid Date | X26: On time delivery | Y26: Delivered | Z26: No | AC26: Not Returned | AD26: Not returned | AE26: Not Applicable
A27: UT-100026 | B27: 45571 | C27: Valid Q4 | D27: CUST_10025 | E27: New | F27: DRS-WRK-M | G27: Dresses | H27: Work Dress | I27: 2699 | J27: 1 | K27: Valid Quantity | L27: 2699 | M27: 2699 | O27: 0 | P27: 0 | Q27: Credit Card | R27: Mobile App | S27: Thiruvananthapuram | T27: Kerala | U27: Bangalore | V27: 45583 | W27: Valid Date | X27: On time delivery | Y27: Delivered | Z27: No | AC27: Not Returned | AD27: Not returned | AE27: Not Applicable
A28: UT-100027 | B28: 45571 | C28: Valid Q4 | D28: CUST_10026 | E28: Returning | F28: OUT-TRN-L | G28: Outerwear | H28: Trench Coat | I28: 4599 | J28: 1 | K28: Valid Quantity | L28: 4599 | M28: 4139.1 | N28: FLAT10 | O28: 10 | P28: 459.9 | Q28: Debit Card | R28: Website | S28: Mysore | T28: Karnataka | U28: Bangalore | V28: 45584 | W28: Valid Date | X28: On time delivery | Y28: Delivered | Z28: Yes | AA28: Size Issue | AB28: 45604 | AC28: Returned | AD28: Valid | AE28: Processed
A29: UT-100028 | B29: 45572 | C29: Valid Q4 | D29: CUST_10027 | E29: New | F29: ACC-HAT-OS | G29: Accessories | H29: Fedora Hat | I29: 1099 | J29: 1 | K29: Valid Quantity | L29: 1099 | M29: 1099 | O29: 0 | P29: 0 | Q29: UPI | R29: Instagram Shop | S29: Vadodara | T29: Gujarat | U29: Mumbai | V29: 45585 | W29: Valid Date | X29: On time delivery | Y29: Delivered | Z29: No | AC29: Not Returned | AD29: Not returned | AE29: Not Applicable
A30: UT-100029 | B30: 45572 | C30: Valid Q4 | D30: CUST_10028 | E30: New | F30: TOP-DNM-M | G30: Tops | H30: Denim Shirt | I30: 1899 | J30: 1 | K30: Valid Quantity | L30: 1899 | M30: 1899 | O30: 0 | P30: 0 | Q30: COD | R30: Mobile App | S30: Rajkot | T30: Gujarat | U30: Mumbai | W30: Not Delivered | X30: Not delivered | Y30: RTO | Z30: No | AC30: Not Delivered | AD30: Not returned | AE30: Not Applicable
A31: UT-100030 | B31: 45572 | C31: Valid Q4 | D31: CUST_10029 | E31: New | F31: BOT-CRG-L | G31: Bottoms | H31: Cargo Pants | I31: 2199 | J31: 1 | K31: Valid Quantity | L31: 2199 | M31: 1759.2 | N31: DIWALI20 | O31: 20 | P31: 439.8 | Q31: Credit Card | R31: Website | S31: Kanpur | T31: Uttar Pradesh | U31: Delhi | V31: 45585 | W31: Valid Date | X31: On time delivery | Y31: Delivered | Z31: No | AC31: Not Returned | AD31: Not returned | AE31: Not Applicable
A32: UT-100031 | B32: 45572 | C32: Valid Q4 | D32: CUST_10030 | E32: Returning | F32: DRS-EVE-S | G32: Dresses | H32: Evening Gown | I32: 5499 | J32: 1 | K32: Valid Quantity | L32: 5499 | M32: 5499 | O32: 0 | P32: 0 | Q32: Credit Card | R32: Mobile App | S32: Mumbai | T32: Maharashtra | U32: Mumbai | V32: 45586 | W32: Valid Date | X32: On time delivery | Y32: Delivered | Z32: Yes | AA32: Size Issue | AB32: 45606 | AC32: Returned | AD32: Valid | AE32: Processed
A33: UT-100032 | B33: 45573 | C33: Valid Q4 | D33: CUST_10031 | E33: New | F33: TOP-BAS-M | G33: Tops | H33: Basic Tank | I33: 899 | J33: 2 | K33: Valid Quantity | L33: 1798 | M33: 1798 | O33: 0 | P33: 0 | Q33: UPI | R33: Website | S33: Delhi | T33: Delhi | U33: Delhi | V33: 45579 | W33: Valid Date | X33: On time delivery | Y33: Delivered | Z33: No | AC33: Not Returned | AD33: Not returned | AE33: Not Applicable
A34: UT-100033 | B34: 45573 | C34: Valid Q4 | D34: CUST_10032 | E34: New | F34: OUT-WOL-L | G34: Outerwear | H34: Wool Coat | I34: 6999 | J34: 1 | K34: Valid Quantity | L34: 6999 | M34: 5949.15 | N34: FIRST15 | O34: 15 | P34: 1049.85 | Q34: Debit Card | R34: Instagram Shop | S34: Kolkata | T34: West Bengal | U34: Delhi | V34: 45581 | W34: Valid Date | X34: On time delivery | Y34: Delivered | Z34: Yes | AA34: Quality Defect | AB34: 45601 | AC34: Returned | AD34: Valid | AE34: Processed
A35: UT-100034 | B35: 45573 | C35: Valid Q4 | D35: CUST_10033 | E35: Returning | F35: ACC-WCH-OS | G35: Accessories | H35: Fashion Watch | I35: 2999 | J35: 1 | K35: Valid Quantity | L35: 2999 | M35: 2999 | O35: 0 | P35: 0 | Q35: Credit Card | R35: Mobile App | S35: Chennai | T35: Tamil Nadu | U35: Bangalore | V35: 45580 | W35: Valid Date | X35: On time delivery | Y35: Delivered | Z35: No | AC35: Not Returned | AD35: Not returned | AE35: Not Applicable
A36: UT-100035 | B36: 45573 | C36: Valid Q4 | D36: CUST_10034 | E36: New | F36: BOT-DNM-S | G36: Bottoms | H36: Denim Shorts | I36: 1599 | J36: 1 | K36: Valid Quantity | L36: 1599 | M36: 1599 | O36: 0 | P36: 0 | Q36: COD | R36: Website | S36: Hyderabad | T36: Telangana | U36: Bangalore | V36: 45582 | W36: Valid Date | X36: On time delivery | Y36: Delivered | Z36: Yes | AA36: Size Issue | AB36: 45604 | AC36: Returned | AD36: Valid | AE36: Processed
A37: UT-100036 | B37: 45574 | C37: Valid Q4 | D37: CUST_10035 | E37: New | F37: DRS-SUN-M | G37: Dresses | H37: Sundress | I37: 1999 | J37: 1 | K37: Valid Quantity | L37: 1999 | M37: 1599.2 | N37: DIWALI20 | O37: 20 | P37: 399.8 | Q37: Wallet | R37: Mobile App | S37: Pune | T37: Maharashtra | U37: Mumbai | V37: 45581 | W37: Valid Date | X37: On time delivery | Y37: Delivered | Z37: No | AC37: Not Returned | AD37: Not returned | AE37: Not Applicable
A38: UT-100037 | B38: 45574 | C38: Valid Q4 | D38: CUST_10036 | E38: New | F38: TOP-RFL-S | G38: Tops | H38: Ruffle Top | I38: 1799 | J38: 1 | K38: Valid Quantity | L38: 1799 | M38: 1799 | O38: 0 | P38: 0 | Q38: UPI | R38: Instagram Shop | S38: Ahmedabad | T38: Gujarat | U38: Mumbai | V38: 45582 | W38: Valid Date | X38: On time delivery | Y38: Delivered | Z38: Yes | AA38: Changed Mind | AB38: 45608 | AC38: Returned | AD38: Valid | AE38: Processed
A39: UT-100038 | B39: 45574 | C39: Valid Q4 | D39: CUST_10037 | E39: Returning | F39: OUT-LTH-M | G39: Outerwear | H39: Leather Jacket | I39: 7999 | J39: 1 | K39: Valid Quantity | L39: 7999 | M39: 7999 | O39: 0 | P39: 0 | Q39: Credit Card | R39: Website | S39: Jaipur | T39: Rajasthan | U39: Delhi | V39: 45583 | W39: Valid Date | X39: On time delivery | Y39: Delivered | Z39: No | AC39: Not Returned | AD39: Not returned | AE39: Not Applicable
A40: UT-100039 | B40: 45574 | C40: Valid Q4 | D40: CUST_10038 | E40: New | F40: ACC-SNG-OS | G40: Accessories | H40: Sunglasses | I40: 1499 | J40: 1 | K40: Valid Quantity | L40: 1499 | M40: 1349.1 | N40: FLAT10 | O40: 10 | P40: 149.9 | Q40: Debit Card | R40: Mobile App | S40: Lucknow | T40: Uttar Pradesh | U40: Delhi | V40: 45582 | W40: Valid Date | X40: On time delivery | Y40: Delivered | Z40: No | AC40: Not Returned | AD40: Not returned | AE40: Not Applicable
A41: UT-100040 | B41: 45575 | C41: Valid Q4 | D41: CUST_10039 | E41: New | F41: BOT-PLZ-L | G41: Bottoms | H41: Palazzo Pants | I41: 1699 | J41: 1 | K41: Valid Quantity | L41: 1699 | M41: 1699 | O41: 0 | P41: 0 | Q41: COD | R41: Website | S41: Bangalore | T41: Karnataka | U41: Bangalore | V41: 45584 | W41: Valid Date | X41: On time delivery | Y41: Delivered | Z41: Yes | AA41: Size Issue | AB41: 45606 | AC41: Returned | AD41: Valid | AE41: Processed
A42: UT-100041 | B42: 45575 | C42: Valid Q4 | D42: CUST_10040 | E42: New | F42: DRS-BDC-S | G42: Dresses | H42: Bodycon Dress | I42: 2299 | J42: 1 | K42: Valid Quantity | L42: 2299 | M42: 2299 | O42: 0 | P42: 0 | Q42: UPI | R42: Instagram Shop | S42: Mumbai | T42: Maharashtra | U42: Mumbai | V42: 45583 | W42: Valid Date | X42: On time delivery | Y42: Delivered | Z42: No | AC42: Not Returned | AD42: Not returned | AE42: Not Applicable
A43: UT-100042 | B43: 45575 | C43: Valid Q4 | D43: CUST_10041 | E43: Returning | F43: TOP-OFF-M | G43: Tops | H43: Off-Shoulder Top | I43: 1599 | J43: 2 | K43: Valid Quantity | L43: 3198 | M43: 2558.4 | N43: DIWALI20 | O43: 20 | P43: 639.6 | Q43: Credit Card | R43: Mobile App | S43: Delhi | T43: Delhi | U43: Delhi | V43: 45582 | W43: Valid Date | X43: On time delivery | Y43: Delivered | Z43: Yes | AA43: Wrong Item | AB43: 45604 | AC43: Returned | AD43: Valid | AE43: Processed
A44: UT-100043 | B44: 45575 | C44: Valid Q4 | D44: CUST_10042 | E44: New | F44: OUT-DNM-L | G44: Outerwear | H44: Denim Vest | I44: 2499 | J44: 1 | K44: Valid Quantity | L44: 2499 | M44: 2499 | O44: 0 | P44: 0 | Q44: Wallet | R44: Website | S44: Chandigarh | T44: Punjab | U44: Delhi | V44: 45585 | W44: Valid Date | X44: On time delivery | Y44: Delivered | Z44: No | AC44: Not Returned | AD44: Not returned | AE44: Not Applicable
A45: UT-100044 | B45: 45576 | C45: Valid Q4 | D45: CUST_10043 | E45: New | F45: ACC-HBG-OS | G45: Accessories | H45: Hobo Bag | I45: 1899 | J45: 1 | K45: Valid Quantity | L45: 1899 | M45: 1899 | O45: 0 | P45: 0 | Q45: Debit Card | R45: Instagram Shop | S45: Noida | T45: Uttar Pradesh | U45: Delhi | V45: 45586 | W45: Valid Date | X45: On time delivery | Y45: Delivered | Z45: Yes | AA45: Damaged in Transit | AB45: 45608 | AC45: Returned | AD45: Valid | AE45: Processed
A46: UT-100045 | B46: 45576 | C46: Valid Q4 | D46: CUST_10044 | E46: New | F46: BOT-CHP-M | G46: Bottoms | H46: Chino Pants | I46: 1999 | J46: 1 | K46: Valid Quantity | L46: 1999 | M46: 1699.15 | N46: FIRST15 | O46: 15 | P46: 299.85 | Q46: UPI | R46: Mobile App | S46: Gurgaon | T46: Haryana | U46: Delhi | V46: 45584 | W46: Valid Date | X46: On time delivery | Y46: Delivered | Z46: No | AC46: Not Returned | AD46: Not returned | AE46: Not Applicable
A47: UT-100046 | B47: 45576 | C47: Valid Q4 | D47: CUST_10045 | E47: Returning | F47: DRS-WRP-M | G47: Dresses | H47: Wrap Dress | I47: 2599 | J47: 1 | K47: Valid Quantity | L47: 2599 | M47: 2599 | O47: 0 | P47: 0 | Q47: Credit Card | R47: Website | S47: Indore | T47: Madhya Pradesh | U47: Mumbai | V47: 45585 | W47: Valid Date | X47: On time delivery | Y47: Delivered | Z47: No | AC47: Not Returned | AD47: Not returned | AE47: Not Applicable
A48: UT-100047 | B48: 45576 | C48: Valid Q4 | D48: CUST_10046 | E48: New | F48: TOP-STR-S | G48: Tops | H48: Striped Tee | I48: 1299 | J48: 1 | K48: Valid Quantity | L48: 1299 | M48: 1299 | O48: 0 | P48: 0 | Q48: COD | R48: Instagram Shop | S48: Surat | T48: Gujarat | U48: Mumbai | W48: Not Delivered | X48: Not delivered | Y48: RTO | Z48: No | AC48: Not Delivered | AD48: Not returned | AE48: Not Applicable
A49: UT-100048 | B49: 45577 | C49: Valid Q4 | D49: CUST_10047 | E49: New | F49: OUT-PRK-XL | G49: Outerwear | H49: Parka Jacket | I49: 5999 | J49: 1 | K49: Valid Quantity | L49: 5999 | M49: 4799.2 | N49: DIWALI20 | O49: 20 | P49: 1199.8 | Q49: Credit Card | R49: Mobile App | S49: Patna | T49: Bihar | U49: Delhi | V49: 45587 | W49: Valid Date | X49: On time delivery | Y49: Delivered | Z49: Yes | AA49: Size Issue | AB49: 45611 | AC49: Returned | AD49: Valid | AE49: Processed
A50: UT-100049 | B50: 45577 | C50: Valid Q4 | D50: CUST_10048 | E50: New | F50: ACC-EAR-OS | G50: Accessories | H50: Hoop Earrings | I50: 799 | J50: 2 | K50: Valid Quantity | L50: 1598 | M50: 1598 | O50: 0 | P50: 0 | Q50: UPI | R50: Website | S50: Bhopal | T50: Madhya Pradesh | U50: Mumbai | V50: 45585 | W50: Valid Date | X50: On time delivery | Y50: Delivered | Z50: No | AC50: Not Returned | AD50: Not returned | AE50: Not Applicable
A51: UT-100050 | B51: 45577 | C51: Valid Q4 | D51: CUST_10049 | E51: Returning | F51: BOT-LGN-S | G51: Bottoms | H51: Leggings | I51: 999 | J51: 2 | K51: Valid Quantity | L51: 1998 | M51: 1998 | O51: 0 | P51: 0 | Q51: Wallet | R51: Mobile App | S51: Nagpur | T51: Maharashtra | U51: Mumbai | V51: 45584 | W51: Valid Date | X51: On time delivery | Y51: Delivered | Z51: No | AC51: Not Returned | AD51: Not returned | AE51: Not Applicable
A52: UT-100051 | B52: 45577 | C52: Valid Q4 | D52: CUST_10050 | E52: New | F52: DRS-CTN-L | G52: Dresses | H52: Cotton Dress | I52: 1899 | J52: 1 | K52: Valid Quantity | L52: 1899 | M52: 1899 | O52: 0 | P52: 0 | Q52: Debit Card | R52: Instagram Shop | S52: Coimbatore | T52: Tamil Nadu | U52: Bangalore | V52: 45587 | W52: Valid Date | X52: On time delivery | Y52: Delivered | Z52: Yes | AA52: Quality Defect | AB52: 45610 | AC52: Returned | AD52: Valid | AE52: Processed
A53: UT-100052 | B53: 45578 | C53: Valid Q4 | D53: CUST_10051 | E53: New | F53: TOP-LCE-M | G53: Tops | H53: Lace Top | I53: 1699 | J53: 1 | K53: Valid Quantity | L53: 1699 | M53: 1529.1 | N53: FLAT10 | O53: 10 | P53: 169.9 | Q53: Credit Card | R53: Website | S53: Kochi | T53: Kerala | U53: Bangalore | V53: 45586 | W53: Valid Date | X53: On time delivery | Y53: Delivered | Z53: No | AC53: Not Returned | AD53: Not returned | AE53: Not Applicable
A54: UT-100053 | B54: 45578 | C54: Valid Q4 | D54: CUST_10052 | E54: New | F54: OUT-BOM-M | G54: Outerwear | H54: Bomber Jacket | I54: 3799 | J54: 1 | K54: Valid Quantity | L54: 3799 | M54: 3799 | O54: 0 | P54: 0 | Q54: UPI | R54: Mobile App | S54: Vizag | T54: Andhra Pradesh | U54: Bangalore | V54: 45588 | W54: Valid Date | X54: On time delivery | Y54: Delivered | Z54: Yes | AA54: Size Issue | AB54: 45614 | AC54: Returned | AD54: Valid | AE54: Processed
A55: UT-100054 | B55: 45578 | C55: Valid Q4 | D55: CUST_10053 | E55: Returning | F55: ACC-NCK-OS | G55: Accessories | H55: Pendant Necklace | I55: 1299 | J55: 1 | K55: Valid Quantity | L55: 1299 | M55: 1299 | O55: 0 | P55: 0 | Q55: COD | R55: Instagram Shop | S55: Thiruvananthapuram | T55: Kerala | U55: Bangalore | V55: 45587 | W55: Valid Date | X55: On time delivery | Y55: Delivered | Z55: No | AC55: Not Returned | AD55: Not returned | AE55: Not Applicable
A56: UT-100055 | B56: 45578 | C56: Valid Q4 | D56: CUST_10054 | E56: New | F56: BOT-WID-M | G56: Bottoms | H56: Wide Leg Pants | I56: 2099 | J56: 1 | K56: Valid Quantity | L56: 2099 | M56: 1679.2 | N56: DIWALI20 | O56: 20 | P56: 419.8 | Q56: Credit Card | R56: Website | S56: Mysore | T56: Karnataka | U56: Bangalore | V56: 45589 | W56: Valid Date | X56: On time delivery | Y56: Delivered | Z56: No | AC56: Not Returned | AD56: Not returned | AE56: Not Applicable
A57: UT-100056 | B57: 45579 | C57: Valid Q4 | D57: CUST_10055 | E57: New | F57: DRS-TIR-S | G57: Dresses | H57: Tiered Dress | I57: 2799 | J57: 1 | K57: Valid Quantity | L57: 2799 | M57: 2799 | O57: 0 | P57: 0 | Q57: Debit Card | R57: Mobile App | S57: Vadodara | T57: Gujarat | U57: Mumbai | V57: 45588 | W57: Valid Date | X57: On time delivery | Y57: Delivered | Z57: Yes | AA57: Changed Mind | AB57: 45612 | AC57: Returned | AD57: Valid | AE57: Processed
A58: UT-100057 | B58: 45579 | C58: Valid Q4 | D58: CUST_10056 | E58: New | F58: TOP-PEP-M | G58: Tops | H58: Peplum Top | I58: 1499 | J58: 1 | K58: Valid Quantity | L58: 1499 | M58: 1499 | O58: 0 | P58: 0 | Q58: Wallet | R58: Website | S58: Rajkot | T58: Gujarat | U58: Mumbai | V58: 45587 | W58: Valid Date | X58: On time delivery | Y58: Delivered | Z58: No | AC58: Not Returned | AD58: Not returned | AE58: Not Applicable
A59: UT-100058 | B59: 45579 | C59: Valid Q4 | D59: CUST_10057 | E59: Returning | F59: OUT-QTD-L | G59: Outerwear | H59: Quilted Jacket | I59: 4499 | J59: 1 | K59: Valid Quantity | L59: 4499 | M59: 3824.15 | N59: FIRST15 | O59: 15 | P59: 674.85 | Q59: UPI | R59: Instagram Shop | S59: Kanpur | T59: Uttar Pradesh | U59: Delhi | V59: 45590 | W59: Valid Date | X59: On time delivery | Y59: Delivered | Z59: Yes | AA59: Wrong Item | AB59: 45616 | AC59: Returned | AD59: Valid | AE59: Processed
A60: UT-100059 | B60: 45579 | C60: Valid Q4 | D60: CUST_10058 | E60: New | F60: ACC-BRC-OS | G60: Accessories | H60: Charm Bracelet | I60: 899 | J60: 1 | K60: Valid Quantity | L60: 899 | M60: 899 | O60: 0 | P60: 0 | Q60: Credit Card | R60: Mobile App | S60: Mumbai | T60: Maharashtra | U60: Mumbai | V60: 45588 | W60: Valid Date | X60: On time delivery | Y60: Delivered | Z60: No | AC60: Not Returned | AD60: Not returned | AE60: Not Applicable
A61: UT-100060 | B61: 45580 | C61: Valid Q4 | D61: CUST_10059 | E61: New | F61: BOT-CRP-S | G61: Bottoms | H61: Cropped Pants | I61: 1799 | J61: 1 | K61: Valid Quantity | L61: 1799 | M61: 1799 | O61: 0 | P61: 0 | Q61: COD | R61: Website | S61: Delhi | T61: Delhi | U61: Delhi | W61: Not Delivered | X61: Not delivered | Y61: RTO | Z61: No | AC61: Not Delivered | AD61: Not returned | AE61: Not Applicable
A62: UT-100061 | B62: 45580 | C62: Valid Q4 | D62: CUST_10060 | E62: New | F62: DRS-SLP-M | G62: Dresses | H62: Slip Dress | I62: 2199 | J62: 1 | K62: Valid Quantity | L62: 2199 | M62: 1759.2 | N62: DIWALI20 | O62: 20 | P62: 439.8 | Q62: Debit Card | R62: Instagram Shop | S62: Kolkata | T62: West Bengal | U62: Delhi | V62: 45591 | W62: Valid Date | X62: On time delivery | Y62: Delivered | Z62: Yes | AA62: Size Issue | AB62: 45618 | AC62: Returned | AD62: Valid | AE62: Processed
A63: UT-100062 | B63: 45580 | C63: Valid Q4 | D63: CUST_10061 | E63: Returning | F63: TOP-HLT-L | G63: Tops | H63: Halter Top | I63: 1399 | J63: 1 | K63: Valid Quantity | L63: 1399 | M63: 1399 | O63: 0 | P63: 0 | Q63: UPI | R63: Mobile App | S63: Chennai | T63: Tamil Nadu | U63: Bangalore | V63: 45589 | W63: Valid Date | X63: On time delivery | Y63: Delivered | Z63: No | AC63: Not Returned | AD63: Not returned | AE63: Not Applicable
A64: UT-100063 | B64: 45580 | C64: Valid Q4 | D64: CUST_10062 | E64: New | F64: OUT-FLC-M | G64: Outerwear | H64: Fleece Jacket | I64: 2999 | J64: 1 | K64: Valid Quantity | L64: 2999 | M64: 2999 | O64: 0 | P64: 0 | Q64: Credit Card | R64: Website | S64: Hyderabad | T64: Telangana | U64: Bangalore | V64: 45592 | W64: Valid Date | X64: On time delivery | Y64: Delivered | Z64: Yes | AA64: Quality Defect | AB64: 45620 | AC64: Returned | AD64: Valid | AE64: Processed
A65: UT-100064 | B65: 45581 | C65: Valid Q4 | D65: CUST_10063 | E65: New | F65: ACC-RNG-OS | G65: Accessories | H65: Cocktail Ring | I65: 699 | J65: 2 | K65: Valid Quantity | L65: 1398 | M65: 1258.2 | N65: FLAT10 | O65: 10 | P65: 139.8 | Q65: Wallet | R65: Instagram Shop | S65: Pune | T65: Maharashtra | U65: Mumbai | V65: 45590 | W65: Valid Date | X65: On time delivery | Y65: Delivered | Z65: No | AC65: Not Returned | AD65: Not returned | AE65: Not Applicable
A66: UT-100065 | B66: 45581 | C66: Valid Q4 | D66: CUST_10064 | E66: New | F66: BOT-SKN-M | G66: Bottoms | H66: Skinny Jeans | I66: 2199 | J66: 1 | K66: Valid Quantity | L66: 2199 | M66: 2199 | O66: 0 | P66: 0 | Q66: COD | R66: Mobile App | S66: Ahmedabad | T66: Gujarat | U66: Mumbai | V66: 45593 | W66: Valid Date | X66: On time delivery | Y66: Delivered | Z66: Yes | AA66: Size Issue | AB66: 45621 | AC66: Returned | AD66: Valid | AE66: Processed
A67: UT-100066 | B67: 45581 | C67: Valid Q4 | D67: CUST_10065 | E67: Returning | F67: DRS-KNT-S | G67: Dresses | H67: Knit Dress | I67: 2499 | J67: 1 | K67: Valid Quantity | L67: 2499 | M67: 2499 | O67: 0 | P67: 0 | Q67: Credit Card | R67: Website | S67: Jaipur | T67: Rajasthan | U67: Delhi | V67: 45591 | W67: Valid Date | X67: On time delivery | Y67: Delivered | Z67: No | AC67: Not Returned | AD67: Not returned | AE67: Not Applicable
A68: UT-100067 | B68: 45581 | C68: Valid Q4 | D68: CUST_10066 | E68: New | F68: TOP-EMB-M | G68: Tops | H68: Embroidered Top | I68: 1899 | J68: 1 | K68: Valid Quantity | L68: 1899 | M68: 1519.2 | N68: DIWALI20 | O68: 20 | P68: 379.8 | Q68: UPI | R68: Instagram Shop | S68: Lucknow | T68: Uttar Pradesh | U68: Delhi | V68: 45592 | W68: Valid Date | X68: On time delivery | Y68: Delivered | Z68: Yes | AA68: Changed Mind | AB68: 45616 | AC68: Returned | AD68: Valid | AE68: Processed
A69: UT-100068 | B69: 45582 | C69: Valid Q4 | D69: CUST_10067 | E69: New | F69: OUT-SHR-L | G69: Outerwear | H69: Shrug | I69: 1299 | J69: 1 | K69: Valid Quantity | L69: 1299 | M69: 1299 | O69: 0 | P69: 0 | Q69: Debit Card | R69: Mobile App | S69: Bangalore | T69: Karnataka | U69: Bangalore | V69: 45593 | W69: Valid Date | X69: On time delivery | Y69: Delivered | Z69: No | AC69: Not Returned | AD69: Not returned | AE69: Not Applicable
A70: UT-100069 | B70: 45582 | C70: Valid Q4 | D70: CUST_10068 | E70: New | F70: ACC-CLT-OS | G70: Accessories | H70: Clutch Bag | I70: 1599 | J70: 1 | K70: Valid Quantity | L70: 1599 | M70: 1599 | O70: 0 | P70: 0 | Q70: Credit Card | R70: Website | S70: Mumbai | T70: Maharashtra | U70: Mumbai | V70: 45592 | W70: Valid Date | X70: On time delivery | Y70: Delivered | Z70: Yes | AA70: Damaged in Transit | AB70: 45618 | AC70: Returned | AD70: Valid | AE70: Processed
A71: UT-100070 | B71: 45582 | C71: Valid Q4 | D71: CUST_10069 | E71: Returning | F71: BOT-FLR-S | G71: Bottoms | H71: Flared Jeans | I71: 2099 | J71: 1 | K71: Valid Quantity | L71: 2099 | M71: 1784.15 | N71: FIRST15 | O71: 15 | P71: 314.85 | Q71: UPI | R71: Instagram Shop | S71: Delhi | T71: Delhi | U71: Delhi | V71: 45594 | W71: Valid Date | X71: On time delivery | Y71: Delivered | Z71: No | AC71: Not Returned | AD71: Not returned | AE71: Not Applicable
A72: UT-100071 | B72: 45582 | C72: Valid Q4 | D72: CUST_10070 | E72: New | F72: DRS-PIN-M | G72: Dresses | H72: Pinafore Dress | I72: 2299 | J72: 1 | K72: Valid Quantity | L72: 2299 | M72: 2299 | O72: 0 | P72: 0 | Q72: COD | R72: Mobile App | S72: Chandigarh | T72: Punjab | U72: Delhi | W72: Not Delivered | X72: Not delivered | Y72: RTO | Z72: No | AC72: Not Delivered | AD72: Not returned | AE72: Not Applicable
A73: UT-100072 | B73: 45583 | C73: Valid Q4 | D73: CUST_10071 | E73: New | F73: TOP-CRW-L | G73: Tops | H73: Crew Neck Tee | I73: 1199 | J73: 2 | K73: Valid Quantity | L73: 2398 | M73: 2398 | O73: 0 | P73: 0 | Q73: Wallet | R73: Website | S73: Noida | T73: Uttar Pradesh | U73: Delhi | V73: 45593 | W73: Valid Date | X73: On time delivery | Y73: Delivered | Z73: No | AC73: Not Returned | AD73: Not returned | AE73: Not Applicable
A74: UT-100073 | B74: 45583 | C74: Valid Q4 | D74: CUST_10072 | E74: New | F74: OUT-CDG-M | G74: Outerwear | H74: Cardigan | I74: 2599 | J74: 1 | K74: Valid Quantity | L74: 2599 | M74: 2079.2 | N74: DIWALI20 | O74: 20 | P74: 519.8 | Q74: Credit Card | R74: Instagram Shop | S74: Gurgaon | T74: Haryana | U74: Delhi | V74: 45595 | W74: Valid Date | X74: On time delivery | Y74: Delivered | Z74: Yes | AA74: Size Issue | AB74: 45622 | AC74: Returned | AD74: Valid | AE74: Processed
A75: UT-100074 | B75: 45583 | C75: Valid Q4 | D75: CUST_10073 | E75: Returning | F75: ACC-SCR-OS | G75: Accessories | H75: Hair Scrunchie | I75: 299 | J75: 5 | K75: Valid Quantity | L75: 1495 | M75: 1495 | O75: 0 | P75: 0 | Q75: UPI | R75: Mobile App | S75: Indore | T75: Madhya Pradesh | U75: Mumbai | V75: 45592 | W75: Valid Date | X75: On time delivery | Y75: Delivered | Z75: No | AC75: Not Returned | AD75: Not returned | AE75: Not Applicable
A76: UT-100075 | B76: 45583 | C76: Valid Q4 | D76: CUST_10074 | E76: New | F76: BOT-PPR-M | G76: Bottoms | H76: Paper Bag Pants | I76: 1899 | J76: 1 | K76: Valid Quantity | L76: 1899 | M76: 1899 | O76: 0 | P76: 0 | Q76: Debit Card | R76: Website | S76: Surat | T76: Gujarat | U76: Mumbai | V76: 45595 | W76: Valid Date | X76: On time delivery | Y76: Delivered | Z76: Yes | AA76: Wrong Item | AB76: 45624 | AC76: Returned | AD76: Valid | AE76: Processed
A77: UT-100076 | B77: 45584 | C77: Valid Q4 | D77: CUST_10075 | E77: New | F77: DRS-SMK-S | G77: Dresses | H77: Smocked Dress | I77: 2199 | J77: 1 | K77: Valid Quantity | L77: 2199 | M77: 2199 | O77: 0 | P77: 0 | Q77: Credit Card | R77: Instagram Shop | S77: Patna | T77: Bihar | U77: Delhi | V77: 45596 | W77: Valid Date | X77: On time delivery | Y77: Delivered | Z77: No | AC77: Not Returned | AD77: Not returned | AE77: Not Applicable
A78: UT-100077 | B78: 45584 | C78: Valid Q4 | D78: CUST_10076 | E78: New | F78: TOP-BTN-M | G78: Tops | H78: Button-Down Shirt | I78: 1799 | J78: 1 | K78: Valid Quantity | L78: 1799 | M78: 1619.1 | N78: FLAT10 | O78: 10 | P78: 179.9 | Q78: COD | R78: Mobile App | S78: Bhopal | T78: Madhya Pradesh | U78: Mumbai | V78: 45594 | W78: Valid Date | X78: On time delivery | Y78: Delivered | Z78: Yes | AA78: Quality Defect | AB78: 45621 | AC78: Returned | AD78: Valid | AE78: Processed
A79: UT-100078 | B79: 45584 | C79: Valid Q4 | D79: CUST_10077 | E79: Returning | F79: OUT-VLV-L | G79: Outerwear | H79: Velvet Blazer | I79: 4999 | J79: 1 | K79: Valid Quantity | L79: 4999 | M79: 4999 | O79: 0 | P79: 0 | Q79: UPI | R79: Website | S79: Nagpur | T79: Maharashtra | U79: Mumbai | V79: 45597 | W79: Valid Date | X79: On time delivery | Y79: Delivered | Z79: No | AC79: Not Returned | AD79: Not returned | AE79: Not Applicable
A80: UT-100079 | B80: 45584 | C80: Valid Q4 | D80: CUST_10078 | E80: New | F80: ACC-TOT-OS | G80: Accessories | H80: Canvas Tote | I80: 999 | J80: 1 | K80: Valid Quantity | L80: 999 | M80: 999 | O80: 0 | P80: 0 | Q80: Wallet | R80: Instagram Shop | S80: Coimbatore | T80: Tamil Nadu | U80: Bangalore | V80: 45595 | W80: Valid Date | X80: On time delivery | Y80: Delivered | Z80: Yes | AA80: Size Issue | AB80: 45624 | AC80: Returned | AD80: Valid | AE80: Processed
A81: UT-100080 | B81: 45585 | C81: Valid Q4 | D81: CUST_10079 | E81: New | F81: BOT-CRG-S | G81: Bottoms | H81: Cargo Shorts | I81: 1499 | J81: 1 | K81: Valid Quantity | L81: 1499 | M81: 1199.2 | N81: DIWALI20 | O81: 20 | P81: 299.8 | Q81: Credit Card | R81: Mobile App | S81: Kochi | T81: Kerala | U81: Bangalore | V81: 45596 | W81: Valid Date | X81: On time delivery | Y81: Delivered | Z81: No | AC81: Not Returned | AD81: Not returned | AE81: Not Applicable
A82: UT-100081 | B82: 45585 | C82: Valid Q4 | D82: CUST_10080 | E82: New | F82: DRS-BTR-M | G82: Dresses | H82: Butterfly Dress | I82: 2899 | J82: 1 | K82: Valid Quantity | L82: 2899 | M82: 2899 | O82: 0 | P82: 0 | Q82: Debit Card | R82: Website | S82: Vizag | T82: Andhra Pradesh | U82: Bangalore | V82: 45598 | W82: Valid Date | X82: On time delivery | Y82: Delivered | Z82: Yes | AA82: Changed Mind | AB82: 45626 | AC82: Returned | AD82: Valid | AE82: Processed
A83: UT-100082 | B83: 45585 | C83: Valid Q4 | D83: CUST_10081 | E83: Returning | F83: TOP-VNK-L | G83: Tops | H83: V-Neck Tee | I83: 1099 | J83: 2 | K83: Valid Quantity | L83: 2198 | M83: 2198 | O83: 0 | P83: 0 | Q83: UPI | R83: Instagram Shop | S83: Thiruvananthapuram | T83: Kerala | U83: Bangalore | V83: 45595 | W83: Valid Date | X83: On time delivery | Y83: Delivered | Z83: No | AC83: Not Returned | AD83: Not returned | AE83: Not Applicable
A84: UT-100083 | B84: 45585 | C84: Valid Q4 | D84: CUST_10082 | E84: New | F84: OUT-TRN-M | G84: Outerwear | H84: Trench Coat | I84: 5499 | J84: 1 | K84: Valid Quantity | L84: 5499 | M84: 4674.15 | N84: FIRST15 | O84: 15 | P84: 824.85 | Q84: Credit Card | R84: Mobile App | S84: Mysore | T84: Karnataka | U84: Bangalore | V84: 45599 | W84: Valid Date | X84: On time delivery | Y84: Delivered | Z84: Yes | AA84: Size Issue | AB84: 45627 | AC84: Returned | AD84: Valid | AE84: Processed
A85: UT-100084 | B85: 45586 | C85: Valid Q4 | D85: CUST_10083 | E85: New | F85: ACC-BDY-OS | G85: Accessories | H85: Body Chain | I85: 799 | J85: 1 | K85: Valid Quantity | L85: 799 | M85: 799 | O85: 0 | P85: 0 | Q85: COD | R85: Website | S85: Vadodara | T85: Gujarat | U85: Mumbai | W85: Not Delivered | X85: Not delivered | Y85: RTO | Z85: No | AC85: Not Delivered | AD85: Not returned | AE85: Not Applicable
A86: UT-100085 | B86: 45586 | C86: Valid Q4 | D86: CUST_10084 | E86: New | F86: BOT-JGR-L | G86: Bottoms | H86: Jogger Pants | I86: 1599 | J86: 1 | K86: Valid Quantity | L86: 1599 | M86: 1599 | O86: 0 | P86: 0 | Q86: Wallet | R86: Instagram Shop | S86: Rajkot | T86: Gujarat | U86: Mumbai | V86: 45598 | W86: Valid Date | X86: On time delivery | Y86: Delivered | Z86: No | AC86: Not Returned | AD86: Not returned | AE86: Not Applicable
A87: UT-100086 | B87: 45586 | C87: Valid Q4 | D87: CUST_10085 | E87: Returning | F87: DRS-RFL-S | G87: Dresses | H87: Ruffle Dress | I87: 2699 | J87: 1 | K87: Valid Quantity | L87: 2699 | M87: 2159.2 | N87: DIWALI20 | O87: 20 | P87: 539.8 | Q87: Credit Card | R87: Mobile App | S87: Kanpur | T87: Uttar Pradesh | U87: Delhi | V87: 45597 | W87: Valid Date | X87: On time delivery | Y87: Delivered | Z87: Yes | AA87: Quality Defect | AB87: 45626 | AC87: Returned | AD87: Valid | AE87: Processed
A88: UT-100087 | B88: 45586 | C88: Valid Q4 | D88: CUST_10086 | E88: New | F88: TOP-SQR-M | G88: Tops | H88: Square Neck Top | I88: 1499 | J88: 1 | K88: Valid Quantity | L88: 1499 | M88: 1499 | O88: 0 | P88: 0 | Q88: UPI | R88: Website | S88: Mumbai | T88: Maharashtra | U88: Mumbai | V88: 45598 | W88: Valid Date | X88: On time delivery | Y88: Delivered | Z88: No | AC88: Not Returned | AD88: Not returned | AE88: Not Applicable
A89: UT-100088 | B89: 45587 | C89: Valid Q4 | D89: CUST_10087 | E89: New | F89: OUT-WND-L | G89: Outerwear | H89: Windbreaker | I89: 3299 | J89: 1 | K89: Valid Quantity | L89: 3299 | M89: 3299 | O89: 0 | P89: 0 | Q89: Debit Card | R89: Instagram Shop | S89: Delhi | T89: Delhi | U89: Delhi | V89: 45600 | W89: Valid Date | X89: On time delivery | Y89: Delivered | Z89: Yes | AA89: Wrong Item | AB89: 45629 | AC89: Returned | AD89: Valid | AE89: Processed
A90: UT-100089 | B90: 45587 | C90: Valid Q4 | D90: CUST_10088 | E90: New | F90: ACC-ANK-OS | G90: Accessories | H90: Anklet | I90: 499 | J90: 2 | K90: Valid Quantity | L90: 998 | M90: 898.2 | N90: FLAT10 | O90: 10 | P90: 99.8 | Q90: Credit Card | R90: Mobile App | S90: Kolkata | T90: West Bengal | U90: Delhi | V90: 45597 | W90: Valid Date | X90: On time delivery | Y90: Delivered | Z90: No | AC90: Not Returned | AD90: Not returned | AE90: Not Applicable
A91: UT-100090 | B91: 45587 | C91: Valid Q4 | D91: CUST_10089 | E91: Returning | F91: BOT-TRS-M | G91: Bottoms | H91: Tailored Trousers | I91: 2399 | J91: 1 | K91: Valid Quantity | L91: 2399 | M91: 2399 | O91: 0 | P91: 0 | Q91: UPI | R91: Website | S91: Chennai | T91: Tamil Nadu | U91: Bangalore | V91: 45599 | W91: Valid Date | X91: On time delivery | Y91: Delivered | Z91: No | AC91: Not Returned | AD91: Not returned | AE91: Not Applicable
A92: UT-100091 | B92: 45587 | C92: Valid Q4 | D92: CUST_10090 | E92: New | F92: DRS-LST-M | G92: Dresses | H92: Lace Trim Dress | I92: 2599 | J92: 1 | K92: Valid Quantity | L92: 2599 | M92: 2599 | O92: 0 | P92: 0 | Q92: COD | R92: Instagram Shop | S92: Hyderabad | T92: Telangana | U92: Bangalore | W92: Not Delivered | X92: Not delivered | Y92: RTO | Z92: No | AC92: Not Delivered | AD92: Not returned | AE92: Not Applicable
A93: UT-100092 | B93: 45588 | C93: Valid Q4 | D93: CUST_10091 | E93: New | F93: TOP-TIE-S | G93: Tops | H93: Tie-Front Top | I93: 1399 | J93: 1 | K93: Valid Quantity | L93: 1399 | M93: 1119.2 | N93: DIWALI20 | O93: 20 | P93: 279.8 | Q93: Wallet | R93: Mobile App | S93: Pune | T93: Maharashtra | U93: Mumbai | V93: 45599 | W93: Valid Date | X93: On time delivery | Y93: Delivered | Z93: Yes | AA93: Size Issue | AB93: 45628 | AC93: Returned | AD93: Valid | AE93: Processed
A94: UT-100093 | B94: 45588 | C94: Valid Q4 | D94: CUST_10092 | E94: New | F94: OUT-PUF-M | G94: Outerwear | H94: Puffer Jacket | I94: 4299 | J94: 1 | K94: Valid Quantity | L94: 4299 | M94: 4299 | O94: 0 | P94: 0 | Q94: Credit Card | R94: Website | S94: Ahmedabad | T94: Gujarat | U94: Mumbai | V94: 45601 | W94: Valid Date | X94: On time delivery | Y94: Delivered | Z94: No | AC94: Not Returned | AD94: Not returned | AE94: Not Applicable
A95: UT-100094 | B95: 45588 | C95: Valid Q4 | D95: CUST_10093 | E95: Returning | F95: ACC-HDR-OS | G95: Accessories | H95: Hairband | I95: 399 | J95: 3 | K95: Valid Quantity | L95: 1197 | M95: 1197 | O95: 0 | P95: 0 | Q95: UPI | R95: Instagram Shop | S95: Jaipur | T95: Rajasthan | U95: Delhi | V95: 45598 | W95: Valid Date | X95: On time delivery | Y95: Delivered | Z95: No | AC95: Not Returned | AD95: Not returned | AE95: Not Applicable
A96: UT-100095 | B96: 45588 | C96: Valid Q4 | D96: CUST_10094 | E96: New | F96: BOT-PLT-L | G96: Bottoms | H96: Pleated Trousers | I96: 2199 | J96: 1 | K96: Valid Quantity | L96: 2199 | M96: 1869.15 | N96: FIRST15 | O96: 15 | P96: 329.85 | Q96: Debit Card | R96: Mobile App | S96: Lucknow | T96: Uttar Pradesh | U96: Delhi | V96: 45601 | W96: Valid Date | X96: On time delivery | Y96: Delivered | Z96: Yes | AA96: Damaged in Transit | AB96: 45631 | AC96: Returned | AD96: Valid | AE96: Processed
A97: UT-100096 | B97: 45589 | C97: Valid Q4 | D97: CUST_10095 | E97: New | F97: DRS-SHR-S | G97: Dresses | H97: Shirtdress | I97: 2399 | J97: 1 | K97: Valid Quantity | L97: 2399 | M97: 2399 | O97: 0 | P97: 0 | Q97: Credit Card | R97: Website | S97: Bangalore | T97: Karnataka | U97: Bangalore | V97: 45600 | W97: Valid Date | X97: On time delivery | Y97: Delivered | Z97: No | AC97: Not Returned | AD97: Not returned | AE97: Not Applicable
A98: UT-100097 | B98: 45589 | C98: Valid Q4 | D98: CUST_10096 | E98: New | F98: TOP-GRF-M | G98: Tops | H98: Graphic Tee | I98: 1299 | J98: 1 | K98: Valid Quantity | L98: 1299 | M98: 1299 | O98: 0 | P98: 0 | Q98: COD | R98: Instagram Shop | S98: Mumbai | T98: Maharashtra | U98: Mumbai | V98: 45602 | W98: Valid Date | X98: On time delivery | Y98: Delivered | Z98: Yes | AA98: Changed Mind | AB98: 45631 | AC98: Returned | AD98: Valid | AE98: Processed
A99: UT-100098 | B99: 45589 | C99: Valid Q4 | D99: CUST_10097 | E99: Returning | F99: OUT-SHW-L | G99: Outerwear | H99: Shawl Wrap | I99: 2799 | J99: 1 | K99: Valid Quantity | L99: 2799 | M99: 2239.2 | N99: DIWALI20 | O99: 20 | P99: 559.8 | Q99: UPI | R99: Mobile App | S99: Delhi | T99: Delhi | U99: Delhi | V99: 45601 | W99: Valid Date | X99: On time delivery | Y99: Delivered | Z99: No | AC99: Not Returned | AD99: Not returned | AE99: Not Applicable
A100: UT-100099 | B100: 45589 | C100: Valid Q4 | D100: CUST_10098 | E100: New | F100: ACC-BLT-S | G100: Accessories | H100: Braided Belt | I100: 699 | J100: 1 | K100: Valid Quantity | L100: 699 | M100: 699 | O100: 0 | P100: 0 | Q100: Wallet | R100: Website | S100: Chandigarh | T100: Punjab | U100: Delhi | V100: 45600 | W100: Valid Date | X100: On time delivery | Y100: Delivered | Z100: No | AC100: Not Returned | AD100: Not returned | AE100: Not Applicable
...

Sheet Cleaned_Data
A1: Order ID | B1: Order Date | C1: Order_Date_Validation_Q4 | D1: Customer ID | E1: Type | F1: Product_SKU | G1: Category | H1: Product Name | I1: Unit Price | J1: Qty | K1: Order_Quantity_Validation | L1: Total | M1: Order_Total_After_Discount | N1: Discount Code | O1: Disc % | P1: Discount_Amount | Q1: Payment | R1: Source | S1: City | T1: State | U1: Warehouse | V1: Delivery Date | W1: Delivery_Date_Validation | X1: Delivery_Time_Validation | Y1: Status | Z1: Return? | AA1: Reason | AB1: Return Received | AC1: Return_Date_Validation | AD1: Return_Window_Validation | AE1: Refund
A2: UT-100004 | B2: 45566 | C2: Valid Q4 | D2: CUST_10004 | E2: New | F2: OUT-JKT-XL | G2: Outerwear | H2: Denim Jacket | I2: 3499 | J2: 1 | K2: Valid Quantity | L2: 3499 | M2: 2974.15 | N2: FIRST15 | O2: 15 | P2: 524.85 | Q2: Debit Card | R2: Instagram Shop | S2: Chennai | T2: Tamil Nadu | U2: Mumbai | V2: 45573 | W2: Valid Date | X2: On time delivery | Y2: Delivered | Z2: Yes | AA2: Quality Defect | AB2: 45585 | AC2: Returned | AD2: Valid | AE2: Processed
A3: UT-100006 | B3: 45567 | C3: Valid Q4 | D3: CUST_10005 | E3: Returning | F3: TOP-FRM-S | G3: Tops | H3: Printed Blouse | I3: 1599 | J3: 2 | K3: Valid Quantity | L3: 3198 | M3: 3198 | O3: 0 | P3: 0 | Q3: Credit Card | R3: Mobile App | S3: Hyderabad | T3: Telangana | U3: Bangalore | V3: 45572 | W3: Valid Date | X3: On time delivery | Y3: Delivered | Z3: Yes | AA3: Changed Mind | AB3: 45583 | AC3: Returned | AD3: Valid | AE3: Processed
A4: UT-100007 | B4: 45567 | C4: Valid Q4 | D4: CUST_10006 | E4: New | F4: DRS-CAS-M | G4: Dresses | H4: A-Line Dress | I4: 2199 | J4: 1 | K4: Valid Quantity | L4: 2199 | M4: 1759.2 | N4: DIWALI20 | O4: 20 | P4: 439.8 | Q4: COD | R4: Website | S4: Pune | T4: Maharashtra | U4: Mumbai | W4: Not Delivered | X4: Not delivered | Y4: Cancelled | Z4: No | AC4: Not Delivered | AD4: Not returned | AE4: Not Applicable
A5: UT-100008 | B5: 45567 | C5: Valid Q4 | D5: CUST_10007 | E5: New | F5: BOT-TRS-L | G5: Bottoms | H5: Formal Trousers | I5: 2299 | J5: 1 | K5: Valid Quantity | L5: 2299 | M5: 2299 | O5: 0 | P5: 0 | Q5: UPI | R5: Mobile App | S5: Kolkata | T5: West Bengal | U5: Delhi | V5: 45575 | W5: Valid Date | X5: On time delivery | Y5: Delivered | Z5: No | AC5: Not Returned | AD5: Not returned | AE5: Not Applicable
A6: UT-100009 | B6: 45567 | C6: Valid Q4 | D6: CUST_10008 | E6: Returning | F6: TOP-CAS-XL | G6: Tops | H6: Oversized Tee | I6: 1399 | J6: 5 | K6: Valid Quantity | L6: 6995 | M6: 6995 | O6: 0 | P6: 0 | Q6: Credit Card | R6: Website | S6: Ahmedabad | T6: Gujarat | U6: Mumbai | V6: 45574 | W6: Valid Date | X6: On time delivery | Y6: Delivered | Z6: Yes | AA6: Size Issue | AB6: 45587 | AC6: Returned | AD6: Valid | AE6: Processed
A7: UT-100011 | B7: 45568 | C7: Valid Q4 | D7: CUST_10010 | E7: New | F7: ACC-BAG-OS | G7: Accessories | H7: Tote Bag | I7: 1299 | J7: 2 | K7: Valid Quantity | L7: 2598 | M7: 2338.2 | N7: FLAT10 | O7: 10 | P7: 259.8 | Q7: Wallet | R7: Website | S7: Lucknow | T7: Uttar Pradesh | U7: Delhi | V7: 45575 | W7: Valid Date | X7: On time delivery | Y7: Delivered | Z7: No | AC7: Not Returned | AD7: Not returned | AE7: Not Applicable
A8: UT-100012 | B8: 45568 | C8: Valid Q4 | D8: CUST_10011 | E8: New | F8: DRS-PRT-S | G8: Dresses | H8: Party Dress | I8: 3299 | J8: 1 | K8: Valid Quantity | L8: 3299 | M8: 3299 | O8: 0 | P8: 0 | Q8: COD | R8: Mobile App | S8: Chandigarh | T8: Punjab | U8: Delhi | W8: Not Delivered | X8: Not delivered | Y8: RTO | Z8: No | AC8: Not Delivered | AD8: Not returned | AE8: Not Applicable
A9: UT-100013 | B9: 45568 | C9: Valid Q4 | D9: CUST_10012 | E9: Returning | F9: TOP-SLK-M | G9: Tops | H9: Silk Blouse | I9: 2499 | J9: 1 | K9: Valid Quantity | L9: 2499 | M9: 2499 | O9: 0 | P9: 0 | Q9: Credit Card | R9: Website | S9: Mumbai | T9: Maharashtra | U9: Mumbai | V9: 45574 | W9: Valid Date | X9: On time delivery | Y9: Delivered | Z9: No | AC9: Not Returned | AD9: Not returned | AE9: Not Applicable
A10: UT-100014 | B10: 45568 | C10: Valid Q4 | D10: CUST_10013 | E10: New | F10: BOT-SKT-S | G10: Bottoms | H10: Pleated Skirt | I10: 1799 | J10: 2 | K10: Valid Quantity | L10: 3598 | M10: 2878.4 | N10: DIWALI20 | O10: 20 | P10: 719.6 | Q10: UPI | R10: Instagram Shop | S10: Delhi | T10: Delhi | U10: Delhi | V10: 45576 | W10: Valid Date | X10: On time delivery | Y10: Delivered | Z10: Yes | AA10: Size Issue | AB10: 45593 | AC10: Returned | AD10: Valid | AE10: Processed
A11: UT-100015 | B11: 45568 | C11: Valid Q4 | D11: CUST_10014 | E11: New | F11: OUT-CRD-L | G11: Outerwear | H11: Knit Cardigan | I11: 2799 | J11: 1 | K11: Valid Quantity | L11: 2799 | M11: 2799 | O11: 0 | P11: 0 | Q11: Debit Card | R11: Mobile App | S11: Bangalore | T11: Karnataka | U11: Bangalore | V11: 45577 | W11: Valid Date | X11: On time delivery | Y11: Delivered | Z11: No | AC11: Not Returned | AD11: Not returned | AE11: Not Applicable
A12: UT-100016 | B12: 45569 | C12: Valid Q4 | D12: CUST_10015 | E12: Returning | F12: ACC-JWL-OS | G12: Accessories | H12: Statement Earrings | I12: 599 | J12: 4 | K12: Valid Quantity | L12: 2396 | M12: 2396 | O12: 0 | P12: 0 | Q12: COD | R12: Website | S12: Noida | T12: Uttar Pradesh | U12: Delhi | V12: 45579 | W12: Valid Date | X12: On time delivery | Y12: Delivered | Z12: Yes | AA12: Damaged in Transit | AB12: 45591 | AC12: Returned | AD12: Valid | AE12: Processed
A13: UT-100017 | B13: 45569 | C13: Valid Q4 | D13: CUST_10016 | E13: New | F13: TOP-CRP-XS | G13: Tops | H13: Crop Top | I13: 999 | J13: 1 | K13: Valid Quantity | L13: 999 | M13: 849.15 | N13: FIRST15 | O13: 15 | P13: 149.85 | Q13: UPI | R13: Mobile App | S13: Gurgaon | T13: Haryana | U13: Delhi | V13: 45577 | W13: Valid Date | X13: On time delivery | Y13: Delivered | Z13: No | AC13: Not Returned | AD13: Not returned | AE13: Not Applicable
A14: UT-100018 | B14: 45569 | C14: Valid Q4 | D14: CUST_10017 | E14: New | F14: DRS-MAX-M | G14: Dresses | H14: Maxi Dress | I14: 2899 | J14: 1 | K14: Valid Quantity | L14: 2899 | M14: 2899 | O14: 0 | P14: 0 | Q14: Credit Card | R14: Website | S14: Indore | T14: Madhya Pradesh | U14: Mumbai | V14: 45579 | W14: Valid Date | X14: On time delivery | Y14: Delivered | Z14: No | AC14: Not Returned | AD14: Not returned | AE14: Not Applicable
A15: UT-100019 | B15: 45569 | C15: Valid Q4 | D15: CUST_10018 | E15: Returning | F15: BOT-JGR-M | G15: Bottoms | H15: Joggers | I15: 1499 | J15: 2 | K15: Valid Quantity | L15: 2998 | M15: 2998 | O15: 0 | P15: 0 | Q15: Wallet | R15: Instagram Shop | S15: Surat | T15: Gujarat | U15: Mumbai | V15: 45578 | W15: Valid Date | X15: On time delivery | Y15: Delivered | Z15: Yes | AA15: Size Issue | AB15: 45595 | AC15: Returned | AD15: Valid | AE15: Processed
A16: UT-100020 | B16: 45570 | C16: Valid Q4 | D16: CUST_10019 | E16: New | F16: OUT-VST-S | G16: Outerwear | H16: Puffer Vest | I16: 3999 | J16: 1 | K16: Valid Quantity | L16: 3999 | M16: 3199.2 | N16: DIWALI20 | O16: 20 | P16: 799.8 | Q16: COD | R16: Website | S16: Patna | T16: Bihar | U16: Delhi | W16: Not Delivered | X16: Not delivered | Y16: RTO | Z16: No | AC16: Not Delivered | AD16: Not returned | AE16: Not Applicable
A17: UT-100021 | B17: 45570 | C17: Valid Q4 | D17: CUST_10020 | E17: New | F17: TOP-TUN-L | G17: Tops | H17: Tunic Top | I17: 1699 | J17: 1 | K17: Valid Quantity | L17: 1699 | M17: 1699 | O17: 0 | P17: 0 | Q17: UPI | R17: Mobile App | S17: Bhopal | T17: Madhya Pradesh | U17: Mumbai | V17: 45580 | W17: Valid Date | X17: On time delivery | Y17: Delivered | Z17: No | AC17: Not Returned | AD17: Not returned | AE17: Not Applicable
A18: UT-100022 | B18: 45570 | C18: Valid Q4 | D18: CUST_10021 | E18: Returning | F18: DRS-SHT-XS | G18: Dresses | H18: Shirt Dress | I18: 2399 | J18: 1 | K18: Valid Quantity | L18: 2399 | M18: 2399 | O18: 0 | P18: 0 | Q18: Credit Card | R18: Website | S18: Nagpur | T18: Maharashtra | U18: Mumbai | V18: 45581 | W18: Valid Date | X18: On time delivery | Y18: Delivered | Z18: Yes | AA18: Quality Defect | AB18: 45598 | AC18: Returned | AD18: Valid | AE18: Processed
A19: UT-100023 | B19: 45570 | C19: Valid Q4 | D19: CUST_10022 | E19: New | F19: ACC-BLT-M | G19: Accessories | H19: Leather Belt | I19: 899 | J19: 1 | K19: Valid Quantity | L19: 899 | M19: 809.1 | N19: FLAT10 | O19: 10 | P19: 89.9 | Q19: Debit Card | R19: Mobile App | S19: Coimbatore | T19: Tamil Nadu | U19: Bangalore | V19: 45582 | W19: Valid Date | X19: On time delivery | Y19: Delivered | Z19: No | AC19: Not Returned | AD19: Not returned | AE19: Not Applicable
A20: UT-100024 | B20: 45571 | C20: Valid Q4 | D20: CUST_10023 | E20: New | F20: BOT-SHT-M | G20: Bottoms | H20: Cotton Shorts | I20: 1199 | J20: 3 | K20: Valid Quantity | L20: 3597 | M20: 3597 | O20: 0 | P20: 0 | Q20: COD | R20: Instagram Shop | S20: Kochi | T20: Kerala | U20: Bangalore | V20: 45583 | W20: Valid Date | X20: On time delivery | Y20: Delivered | Z20: Yes | AA20: Changed Mind | AB20: 45601 | AC20: Returned | AD20: Valid | AE20: Processed
A21: UT-100025 | B21: 45571 | C21: Valid Q4 | D21: CUST_10024 | E21: New | F21: TOP-PLO-L | G21: Tops | H21: Polo Shirt | I21: 1799 | J21: 2 | K21: Valid Quantity | L21: 3598 | M21: 3598 | O21: 0 | P21: 0 | Q21: UPI | R21: Website | S21: Vizag | T21: Andhra Pradesh | U21: Bangalore | V21: 45582 | W21: Valid Date | X21: On time delivery | Y21: Delivered | Z21: No | AC21: Not Returned | AD21: Not returned | AE21: Not Applicable
A22: UT-100026 | B22: 45571 | C22: Valid Q4 | D22: CUST_10025 | E22: New | F22: DRS-WRK-M | G22: Dresses | H22: Work Dress | I22: 2699 | J22: 1 | K22: Valid Quantity | L22: 2699 | M22: 2699 | O22: 0 | P22: 0 | Q22: Credit Card | R22: Mobile App | S22: Thiruvananthapuram | T22: Kerala | U22: Bangalore | V22: 45583 | W22: Valid Date | X22: On time delivery | Y22: Delivered | Z22: No | AC22: Not Returned | AD22: Not returned | AE22: Not Applicable
A23: UT-100027 | B23: 45571 | C23: Valid Q4 | D23: CUST_10026 | E23: Returning | F23: OUT-TRN-L | G23: Outerwear | H23: Trench Coat | I23: 4599 | J23: 1 | K23: Valid Quantity | L23: 4599 | M23: 4139.1 | N23: FLAT10 | O23: 10 | P23: 459.9 | Q23: Debit Card | R23: Website | S23: Mysore | T23: Karnataka | U23: Bangalore | V23: 45584 | W23: Valid Date | X23: On time delivery | Y23: Delivered | Z23: Yes | AA23: Size Issue | AB23: 45604 | AC23: Returned | AD23: Valid | AE23: Processed
A24: UT-100028 | B24: 45572 | C24: Valid Q4 | D24: CUST_10027 | E24: New | F24: ACC-HAT-OS | G24: Accessories | H24: Fedora Hat | I24: 1099 | J24: 1 | K24: Valid Quantity | L24: 1099 | M24: 1099 | O24: 0 | P24: 0 | Q24: UPI | R24: Instagram Shop | S24: Vadodara | T24: Gujarat | U24: Mumbai | V24: 45585 | W24: Valid Date | X24: On time delivery | Y24: Delivered | Z24: No | AC24: Not Returned | AD24: Not returned | AE24: Not Applicable
A25: UT-100029 | B25: 45572 | C25: Valid Q4 | D25: CUST_10028 | E25: New | F25: TOP-DNM-M | G25: Tops | H25: Denim Shirt | I25: 1899 | J25: 1 | K25: Valid Quantity | L25: 1899 | M25: 1899 | O25: 0 | P25: 0 | Q25: COD | R25: Mobile App | S25: Rajkot | T25: Gujarat | U25: Mumbai | W25: Not Delivered | X25: Not delivered | Y25: RTO | Z25: No | AC25: Not Delivered | AD25: Not returned | AE25: Not Applicable
A26: UT-100030 | B26: 45572 | C26: Valid Q4 | D26: CUST_10029 | E26: New | F26: BOT-CRG-L | G26: Bottoms | H26: Cargo Pants | I26: 2199 | J26: 1 | K26: Valid Quantity | L26: 2199 | M26: 1759.2 | N26: DIWALI20 | O26: 20 | P26: 439.8 | Q26: Credit Card | R26: Website | S26: Kanpur | T26: Uttar Pradesh | U26: Delhi | V26: 45585 | W26: Valid Date | X26: On time delivery | Y26: Delivered | Z26: No | AC26: Not Returned | AD26: Not returned | AE26: Not Applicable
A27: UT-100031 | B27: 45572 | C27: Valid Q4 | D27: CUST_10030 | E27: Returning | F27: DRS-EVE-S | G27: Dresses | H27: Evening Gown | I27: 5499 | J27: 1 | K27: Valid Quantity | L27: 5499 | M27: 5499 | O27: 0 | P27: 0 | Q27: Credit Card | R27: Mobile App | S27: Mumbai | T27: Maharashtra | U27: Mumbai | V27: 45586 | W27: Valid Date | X27: On time delivery | Y27: Delivered | Z27: Yes | AA27: Size Issue | AB27: 45606 | AC27: Returned | AD27: Valid | AE27: Processed
A28: UT-100032 | B28: 45573 | C28: Valid Q4 | D28: CUST_10031 | E28: New | F28: TOP-BAS-M | G28: Tops | H28: Basic Tank | I28: 899 | J28: 2 | K28: Valid Quantity | L28: 1798 | M28: 1798 | O28: 0 | P28: 0 | Q28: UPI | R28: Website | S28: Delhi | T28: Delhi | U28: Delhi | V28: 45579 | W28: Valid Date | X28: On time delivery | Y28: Delivered | Z28: No | AC28: Not Returned | AD28: Not returned | AE28: Not Applicable
A29: UT-100033 | B29: 45573 | C29: Valid Q4 | D29: CUST_10032 | E29: New | F29: OUT-WOL-L | G29: Outerwear | H29: Wool Coat | I29: 6999 | J29: 1 | K29: Valid Quantity | L29: 6999 | M29: 5949.15 | N29: FIRST15 | O29: 15 | P29: 1049.85 | Q29: Debit Card | R29: Instagram Shop | S29: Kolkata | T29: West Bengal | U29: Delhi | V29: 45581 | W29: Valid Date | X29: On time delivery | Y29: Delivered | Z29: Yes | AA29: Quality Defect | AB29: 45601 | AC29: Returned | AD29: Valid | AE29: Processed
A30: UT-100034 | B30: 45573 | C30: Valid Q4 | D30: CUST_10033 | E30: Returning | F30: ACC-WCH-OS | G30: Accessories | H30: Fashion Watch | I30: 2999 | J30: 1 | K30: Valid Quantity | L30: 2999 | M30: 2999 | O30: 0 | P30: 0 | Q30: Credit Card | R30: Mobile App | S30: Chennai | T30: Tamil Nadu | U30: Bangalore | V30: 45580 | W30: Valid Date | X30: On time delivery | Y30: Delivered | Z30: No | AC30: Not Returned | AD30: Not returned | AE30: Not Applicable
A31: UT-100035 | B31: 45573 | C31: Valid Q4 | D31: CUST_10034 | E31: New | F31: BOT-DNM-S | G31: Bottoms | H31: Denim Shorts | I31: 1599 | J31: 1 | K31: Valid Quantity | L31: 1599 | M31: 1599 | O31: 0 | P31: 0 | Q31: COD | R31: Website | S31: Hyderabad | T31: Telangana | U31: Bangalore | V31: 45582 | W31: Valid Date | X31: On time delivery | Y31: Delivered | Z31: Yes | AA31: Size Issue | AB31: 45604 | AC31: Returned | AD31: Valid | AE31: Processed
A32: UT-100036 | B32: 45574 | C32: Valid Q4 | D32: CUST_10035 | E32: New | F32: DRS-SUN-M | G32: Dresses | H32: Sundress | I32: 1999 | J32: 1 | K32: Valid Quantity | L32: 1999 | M32: 1599.2 | N32: DIWALI20 | O32: 20 | P32: 399.8 | Q32: Wallet | R32: Mobile App | S32: Pune | T32: Maharashtra | U32: Mumbai | V32: 45581 | W32: Valid Date | X32: On time delivery | Y32: Delivered | Z32: No | AC32: Not Returned | AD32: Not returned | AE32: Not Applicable
A33: UT-100037 | B33: 45574 | C33: Valid Q4 | D33: CUST_10036 | E33: New | F33: TOP-RFL-S | G33: Tops | H33: Ruffle Top | I33: 1799 | J33: 1 | K33: Valid Quantity | L33: 1799 | M33: 1799 | O33: 0 | P33: 0 | Q33: UPI | R33: Instagram Shop | S33: Ahmedabad | T33: Gujarat | U33: Mumbai | V33: 45582 | W33: Valid Date | X33: On time delivery | Y33: Delivered | Z33: Yes | AA33: Changed Mind | AB33: 45608 | AC33: Returned | AD33: Valid | AE33: Processed
A34: UT-100038 | B34: 45574 | C34: Valid Q4 | D34: CUST_10037 | E34: Returning | F34: OUT-LTH-M | G34: Outerwear | H34: Leather Jacket | I34: 7999 | J34: 1 | K34: Valid Quantity | L34: 7999 | M34: 7999 | O34: 0 | P34: 0 | Q34: Credit Card | R34: Website | S34: Jaipur | T34: Rajasthan | U34: Delhi | V34: 45583 | W34: Valid Date | X34: On time delivery | Y34: Delivered | Z34: No | AC34: Not Returned | AD34: Not returned | AE34: Not Applicable
A35: UT-100039 | B35: 45574 | C35: Valid Q4 | D35: CUST_10038 | E35: New | F35: ACC-SNG-OS | G35: Accessories | H35: Sunglasses | I35: 1499 | J35: 1 | K35: Valid Quantity | L35: 1499 | M35: 1349.1 | N35: FLAT10 | O35: 10 | P35: 149.9 | Q35: Debit Card | R35: Mobile App | S35: Lucknow | T35: Uttar Pradesh | U35: Delhi | V35: 45582 | W35: Valid Date | X35: On time delivery | Y35: Delivered | Z35: No | AC35: Not Returned | AD35: Not returned | AE35: Not Applicable
A36: UT-100040 | B36: 45575 | C36: Valid Q4 | D36: CUST_10039 | E36: New | F36: BOT-PLZ-L | G36: Bottoms | H36: Palazzo Pants | I36: 1699 | J36: 1 | K36: Valid Quantity | L36: 1699 | M36: 1699 | O36: 0 | P36: 0 | Q36: COD | R36: Website | S36: Bangalore | T36: Karnataka | U36: Bangalore | V36: 45584 | W36: Valid Date | X36: On time delivery | Y36: Delivered | Z36: Yes | AA36: Size Issue | AB36: 45606 | AC36: Returned | AD36: Valid | AE36: Processed
A37: UT-100041 | B37: 45575 | C37: Valid Q4 | D37: CUST_10040 | E37: New | F37: DRS-BDC-S | G37: Dresses | H37: Bodycon Dress | I37: 2299 | J37: 1 | K37: Valid Quantity | L37: 2299 | M37: 2299 | O37: 0 | P37: 0 | Q37: UPI | R37: Instagram Shop | S37: Mumbai | T37: Maharashtra | U37: Mumbai | V37: 45583 | W37: Valid Date | X37: On time delivery | Y37: Delivered | Z37: No | AC37: Not Returned | AD37: Not returned | AE37: Not Applicable
A38: UT-100042 | B38: 45575 | C38: Valid Q4 | D38: CUST_10041 | E38: Returning | F38: TOP-OFF-M | G38: Tops | H38: Off-Shoulder Top | I38: 1599 | J38: 2 | K38: Valid Quantity | L38: 3198 | M38: 2558.4 | N38: DIWALI20 | O38: 20 | P38: 639.6 | Q38: Credit Card | R38: Mobile App | S38: Delhi | T38: Delhi | U38: Delhi | V38: 45582 | W38: Valid Date | X38: On time delivery | Y38: Delivered | Z38: Yes | AA38: Wrong Item | AB38: 45604 | AC38: Returned | AD38: Valid | AE38: Processed
A39: UT-100043 | B39: 45575 | C39: Valid Q4 | D39: CUST_10042 | E39: New | F39: OUT-DNM-L | G39: Outerwear | H39: Denim Vest | I39: 2499 | J39: 1 | K39: Valid Quantity | L39: 2499 | M39: 2499 | O39: 0 | P39: 0 | Q39: Wallet | R39: Website | S39: Chandigarh | T39: Punjab | U39: Delhi | V39: 45585 | W39: Valid Date | X39: On time delivery | Y39: Delivered | Z39: No | AC39: Not Returned | AD39: Not returned | AE39: Not Applicable
A40: UT-100044 | B40: 45576 | C40: Valid Q4 | D40: CUST_10043 | E40: New | F40: ACC-HBG-OS | G40: Accessories | H40: Hobo Bag | I40: 1899 | J40: 1 | K40: Valid Quantity | L40: 1899 | M40: 1899 | O40: 0 | P40: 0 | Q40: Debit Card | R40: Instagram Shop | S40: Noida | T40: Uttar Pradesh | U40: Delhi | V40: 45586 | W40: Valid Date | X40: On time delivery | Y40: Delivered | Z40: Yes | AA40: Damaged in Transit | AB40: 45608 | AC40: Returned | AD40: Valid | AE40: Processed
A41: UT-100045 | B41: 45576 | C41: Valid Q4 | D41: CUST_10044 | E41: New | F41: BOT-CHP-M | G41: Bottoms | H41: Chino Pants | I41: 1999 | J41: 1 | K41: Valid Quantity | L41: 1999 | M41: 1699.15 | N41: FIRST15 | O41: 15 | P41: 299.85 | Q41: UPI | R41: Mobile App | S41: Gurgaon | T41: Haryana | U41: Delhi | V41: 45584 | W41: Valid Date | X41: On time delivery | Y41: Delivered | Z41: No | AC41: Not Returned | AD41: Not returned | AE41: Not Applicable
A42: UT-100046 | B42: 45576 | C42: Valid Q4 | D42: CUST_10045 | E42: Returning | F42: DRS-WRP-M | G42: Dresses | H42: Wrap Dress | I42: 2599 | J42: 1 | K42: Valid Quantity | L42: 2599 | M42: 2599 | O42: 0 | P42: 0 | Q42: Credit Card | R42: Website | S42: Indore | T42: Madhya Pradesh | U42: Mumbai | V42: 45585 | W42: Valid Date | X42: On time delivery | Y42: Delivered | Z42: No | AC42: Not Returned | AD42: Not returned | AE42: Not Applicable
A43: UT-100047 | B43: 45576 | C43: Valid Q4 | D43: CUST_10046 | E43: New | F43: TOP-STR-S | G43: Tops | H43: Striped Tee | I43: 1299 | J43: 1 | K43: Valid Quantity | L43: 1299 | M43: 1299 | O43: 0 | P43: 0 | Q43: COD | R43: Instagram Shop | S43: Surat | T43: Gujarat | U43: Mumbai | W43: Not Delivered | X43: Not delivered | Y43: RTO | Z43: No | AC43: Not Delivered | AD43: Not returned | AE43: Not Applicable
A44: UT-100048 | B44: 45577 | C44: Valid Q4 | D44: CUST_10047 | E44: New | F44: OUT-PRK-XL | G44: Outerwear | H44: Parka Jacket | I44: 5999 | J44: 1 | K44: Valid Quantity | L44: 5999 | M44: 4799.2 | N44: DIWALI20 | O44: 20 | P44: 1199.8 | Q44: Credit Card | R44: Mobile App | S44: Patna | T44: Bihar | U44: Delhi | V44: 45587 | W44: Valid Date | X44: On time delivery | Y44: Delivered | Z44: Yes | AA44: Size Issue | AB44: 45611 | AC44: Returned | AD44: Valid | AE44: Processed
A45: UT-100049 | B45: 45577 | C45: Valid Q4 | D45: CUST_10048 | E45: New | F45: ACC-EAR-OS | G45: Accessories | H45: Hoop Earrings | I45: 799 | J45: 2 | K45: Valid Quantity | L45: 1598 | M45: 1598 | O45: 0 | P45: 0 | Q45: UPI | R45: Website | S45: Bhopal | T45: Madhya Pradesh | U45: Mumbai | V45: 45585 | W45: Valid Date | X45: On time delivery | Y45: Delivered | Z45: No | AC45: Not Returned | AD45: Not returned | AE45: Not Applicable
A46: UT-100050 | B46: 45577 | C46: Valid Q4 | D46: CUST_10049 | E46: Returning | F46: BOT-LGN-S | G46: Bottoms | H46: Leggings | I46: 999 | J46: 2 | K46: Valid Quantity | L46: 1998 | M46: 1998 | O46: 0 | P46: 0 | Q46: Wallet | R46: Mobile App | S46: Nagpur | T46: Maharashtra | U46: Mumbai | V46: 45584 | W46: Valid Date | X46: On time delivery | Y46: Delivered | Z46: No | AC46: Not Returned | AD46: Not returned | AE46: Not Applicable
A47: UT-100051 | B47: 45577 | C47: Valid Q4 | D47: CUST_10050 | E47: New | F47: DRS-CTN-L | G47: Dresses | H47: Cotton Dress | I47: 1899 | J47: 1 | K47: Valid Quantity | L47: 1899 | M47: 1899 | O47: 0 | P47: 0 | Q47: Debit Card | R47: Instagram Shop | S47: Coimbatore | T47: Tamil Nadu | U47: Bangalore | V47: 45587 | W47: Valid Date | X47: On time delivery | Y47: Delivered | Z47: Yes | AA47: Quality Defect | AB47: 45610 | AC47: Returned | AD47: Valid | AE47: Processed
A48: UT-100052 | B48: 45578 | C48: Valid Q4 | D48: CUST_10051 | E48: New | F48: TOP-LCE-M | G48: Tops | H48: Lace Top | I48: 1699 | J48: 1 | K48: Valid Quantity | L48: 1699 | M48: 1529.1 | N48: FLAT10 | O48: 10 | P48: 169.9 | Q48: Credit Card | R48: Website | S48: Kochi | T48: Kerala | U48: Bangalore | V48: 45586 | W48: Valid Date | X48: On time delivery | Y48: Delivered | Z48: No | AC48: Not Returned | AD48: Not returned | AE48: Not Applicable
A49: UT-100053 | B49: 45578 | C49: Valid Q4 | D49: CUST_10052 | E49: New | F49: OUT-BOM-M | G49: Outerwear | H49: Bomber Jacket | I49: 3799 | J49: 1 | K49: Valid Quantity | L49: 3799 | M49: 3799 | O49: 0 | P49: 0 | Q49: UPI | R49: Mobile App | S49: Vizag | T49: Andhra Pradesh | U49: Bangalore | V49: 45588 | W49: Valid Date | X49: On time delivery | Y49: Delivered | Z49: Yes | AA49: Size Issue | AB49: 45614 | AC49: Returned | AD49: Valid | AE49: Processed
A50: UT-100054 | B50: 45578 | C50: Valid Q4 | D50: CUST_10053 | E50: Returning | F50: ACC-NCK-OS | G50: Accessories | H50: Pendant Necklace | I50: 1299 | J50: 1 | K50: Valid Quantity | L50: 1299 | M50: 1299 | O50: 0 | P50: 0 | Q50: COD | R50: Instagram Shop | S50: Thiruvananthapuram | T50: Kerala | U50: Bangalore | V50: 45587 | W50: Valid Date | X50: On time delivery | Y50: Delivered | Z50: No | AC50: Not Returned | AD50: Not returned | AE50: Not Applicable
A51: UT-100055 | B51: 45578 | C51: Valid Q4 | D51: CUST_10054 | E51: New | F51: BOT-WID-M | G51: Bottoms | H51: Wide Leg Pants | I51: 2099 | J51: 1 | K51: Valid Quantity | L51: 2099 | M51: 1679.2 | N51: DIWALI20 | O51: 20 | P51: 419.8 | Q51: Credit Card | R51: Website | S51: Mysore | T51: Karnataka | U51: Bangalore | V51: 45589 | W51: Valid Date | X51: On time delivery | Y51: Delivered | Z51: No | AC51: Not Returned | AD51: Not returned | AE51: Not Applicable
A52: UT-100056 | B52: 45579 | C52: Valid Q4 | D52: CUST_10055 | E52: New | F52: DRS-TIR-S | G52: Dresses | H52: Tiered Dress | I52: 2799 | J52: 1 | K52: Valid Quantity | L52: 2799 | M52: 2799 | O52: 0 | P52: 0 | Q52: Debit Card | R52: Mobile App | S52: Vadodara | T52: Gujarat | U52: Mumbai | V52: 45588 | W52: Valid Date | X52: On time delivery | Y52: Delivered | Z52: Yes | AA52: Changed Mind | AB52: 45612 | AC52: Returned | AD52: Valid | AE52: Processed
A53: UT-100057 | B53: 45579 | C53: Valid Q4 | D53: CUST_10056 | E53: New | F53: TOP-PEP-M | G53: Tops | H53: Peplum Top | I53: 1499 | J53: 1 | K53: Valid Quantity | L53: 1499 | M53: 1499 | O53: 0 | P53: 0 | Q53: Wallet | R53: Website | S53: Rajkot | T53: Gujarat | U53: Mumbai | V53: 45587 | W53: Valid Date | X53: On time delivery | Y53: Delivered | Z53: No | AC53: Not Returned | AD53: Not returned | AE53: Not Applicable
A54: UT-100058 | B54: 45579 | C54: Valid Q4 | D54: CUST_10057 | E54: Returning | F54: OUT-QTD-L | G54: Outerwear | H54: Quilted Jacket | I54: 4499 | J54: 1 | K54: Valid Quantity | L54: 4499 | M54: 3824.15 | N54: FIRST15 | O54: 15 | P54: 674.85 | Q54: UPI | R54: Instagram Shop | S54: Kanpur | T54: Uttar Pradesh | U54: Delhi | V54: 45590 | W54: Valid Date | X54: On time delivery | Y54: Delivered | Z54: Yes | AA54: Wrong Item | AB54: 45616 | AC54: Returned | AD54: Valid | AE54: Processed
A55: UT-100059 | B55: 45579 | C55: Valid Q4 | D55: CUST_10058 | E55: New | F55: ACC-BRC-OS | G55: Accessories | H55: Charm Bracelet | I55: 899 | J55: 1 | K55: Valid Quantity | L55: 899 | M55: 899 | O55: 0 | P55: 0 | Q55: Credit Card | R55: Mobile App | S55: Mumbai | T55: Maharashtra | U55: Mumbai | V55: 45588 | W55: Valid Date | X55: On time delivery | Y55: Delivered | Z55: No | AC55: Not Returned | AD55: Not returned | AE55: Not Applicable
A56: UT-100060 | B56: 45580 | C56: Valid Q4 | D56: CUST_10059 | E56: New | F56: BOT-CRP-S | G56: Bottoms | H56: Cropped Pants | I56: 1799 | J56: 1 | K56: Valid Quantity | L56: 1799 | M56: 1799 | O56: 0 | P56: 0 | Q56: COD | R56: Website | S56: Delhi | T56: Delhi | U56: Delhi | W56: Not Delivered | X56: Not delivered | Y56: RTO | Z56: No | AC56: Not Delivered | AD56: Not returned | AE56: Not Applicable
A57: UT-100061 | B57: 45580 | C57: Valid Q4 | D57: CUST_10060 | E57: New | F57: DRS-SLP-M | G57: Dresses | H57: Slip Dress | I57: 2199 | J57: 1 | K57: Valid Quantity | L57: 2199 | M57: 1759.2 | N57: DIWALI20 | O57: 20 | P57: 439.8 | Q57: Debit Card | R57: Instagram Shop | S57: Kolkata | T57: West Bengal | U57: Delhi | V57: 45591 | W57: Valid Date | X57: On time delivery | Y57: Delivered | Z57: Yes | AA57: Size Issue | AB57: 45618 | AC57: Returned | AD57: Valid | AE57: Processed
A58: UT-100062 | B58: 45580 | C58: Valid Q4 | D58: CUST_10061 | E58: Returning | F58: TOP-HLT-L | G58: Tops | H58: Halter Top | I58: 1399 | J58: 1 | K58: Valid Quantity | L58: 1399 | M58: 1399 | O58: 0 | P58: 0 | Q58: UPI | R58: Mobile App | S58: Chennai | T58: Tamil Nadu | U58: Bangalore | V58: 45589 | W58: Valid Date | X58: On time delivery | Y58: Delivered | Z58: No | AC58: Not Returned | AD58: Not returned | AE58: Not Applicable
A59: UT-100063 | B59: 45580 | C59: Valid Q4 | D59: CUST_10062 | E59: New | F59: OUT-FLC-M | G59: Outerwear | H59: Fleece Jacket | I59: 2999 | J59: 1 | K59: Valid Quantity | L59: 2999 | M59: 2999 | O59: 0 | P59: 0 | Q59: Credit Card | R59: Website | S59: Hyderabad | T59: Telangana | U59: Bangalore | V59: 45592 | W59: Valid Date | X59: On time delivery | Y59: Delivered | Z59: Yes | AA59: Quality Defect | AB59: 45620 | AC59: Returned | AD59: Valid | AE59: Processed
A60: UT-100064 | B60: 45581 | C60: Valid Q4 | D60: CUST_10063 | E60: New | F60: ACC-RNG-OS | G60: Accessories | H60: Cocktail Ring | I60: 699 | J60: 2 | K60: Valid Quantity | L60: 1398 | M60: 1258.2 | N60: FLAT10 | O60: 10 | P60: 139.8 | Q60: Wallet | R60: Instagram Shop | S60: Pune | T60: Maharashtra | U60: Mumbai | V60: 45590 | W60: Valid Date | X60: On time delivery | Y60: Delivered | Z60: No | AC60: Not Returned | AD60: Not returned | AE60: Not Applicable
A61: UT-100065 | B61: 45581 | C61: Valid Q4 | D61: CUST_10064 | E61: New | F61: BOT-SKN-M | G61: Bottoms | H61: Skinny Jeans | I61: 2199 | J61: 1 | K61: Valid Quantity | L61: 2199 | M61: 2199 | O61: 0 | P61: 0 | Q61: COD | R61: Mobile App | S61: Ahmedabad | T61: Gujarat | U61: Mumbai | V61: 45593 | W61: Valid Date | X61: On time delivery | Y61: Delivered | Z61: Yes | AA61: Size Issue | AB61: 45621 | AC61: Returned | AD61: Valid | AE61: Processed
A62: UT-100066 | B62: 45581 | C62: Valid Q4 | D62: CUST_10065 | E62: Returning | F62: DRS-KNT-S | G62: Dresses | H62: Knit Dress | I62: 2499 | J62: 1 | K62: Valid Quantity | L62: 2499 | M62: 2499 | O62: 0 | P62: 0 | Q62: Credit Card | R62: Website | S62: Jaipur | T62: Rajasthan | U62: Delhi | V62: 45591 | W62: Valid Date | X62: On time delivery | Y62: Delivered | Z62: No | AC62: Not Returned | AD62: Not returned | AE62: Not Applicable
A63: UT-100067 | B63: 45581 | C63: Valid Q4 | D63: CUST_10066 | E63: New | F63: TOP-EMB-M | G63: Tops | H63: Embroidered Top | I63: 1899 | J63: 1 | K63: Valid Quantity | L63: 1899 | M63: 1519.2 | N63: DIWALI20 | O63: 20 | P63: 379.8 | Q63: UPI | R63: Instagram Shop | S63: Lucknow | T63: Uttar Pradesh | U63: Delhi | V63: 45592 | W63: Valid Date | X63: On time delivery | Y63: Delivered | Z63: Yes | AA63: Changed Mind | AB63: 45616 | AC63: Returned | AD63: Valid | AE63: Processed
A64: UT-100068 | B64: 45582 | C64: Valid Q4 | D64: CUST_10067 | E64: New | F64: OUT-SHR-L | G64: Outerwear | H64: Shrug | I64: 1299 | J64: 1 | K64: Valid Quantity | L64: 1299 | M64: 1299 | O64: 0 | P64: 0 | Q64: Debit Card | R64: Mobile App | S64: Bangalore | T64: Karnataka | U64: Bangalore | V64: 45593 | W64: Valid Date | X64: On time delivery | Y64: Delivered | Z64: No | AC64: Not Returned | AD64: Not returned | AE64: Not Applicable
A65: UT-100069 | B65: 45582 | C65: Valid Q4 | D65: CUST_10068 | E65: New | F65: ACC-CLT-OS | G65: Accessories | H65: Clutch Bag | I65: 1599 | J65: 1 | K65: Valid Quantity | L65: 1599 | M65: 1599 | O65: 0 | P65: 0 | Q65: Credit Card | R65: Website | S65: Mumbai | T65: Maharashtra | U65: Mumbai | V65: 45592 | W65: Valid Date | X65: On time delivery | Y65: Delivered | Z65: Yes | AA65: Damaged in Transit | AB65: 45618 | AC65: Returned | AD65: Valid | AE65: Processed
A66: UT-100070 | B66: 45582 | C66: Valid Q4 | D66: CUST_10069 | E66: Returning | F66: BOT-FLR-S | G66: Bottoms | H66: Flared Jeans | I66: 2099 | J66: 1 | K66: Valid Quantity | L66: 2099 | M66: 1784.15 | N66: FIRST15 | O66: 15 | P66: 314.85 | Q66: UPI | R66: Instagram Shop | S66: Delhi | T66: Delhi | U66: Delhi | V66: 45594 | W66: Valid Date | X66: On time delivery | Y66: Delivered | Z66: No | AC66: Not Returned | AD66: Not returned | AE66: Not Applicable
A67: UT-100071 | B67: 45582 | C67: Valid Q4 | D67: CUST_10070 | E67: New | F67: DRS-PIN-M | G67: Dresses | H67: Pinafore Dress | I67: 2299 | J67: 1 | K67: Valid Quantity | L67: 2299 | M67: 2299 | O67: 0 | P67: 0 | Q67: COD | R67: Mobile App | S67: Chandigarh | T67: Punjab | U67: Delhi | W67: Not Delivered | X67: Not delivered | Y67: RTO | Z67: No | AC67: Not Delivered | AD67: Not returned | AE67: Not Applicable
A68: UT-100072 | B68: 45583 | C68: Valid Q4 | D68: CUST_10071 | E68: New | F68: TOP-CRW-L | G68: Tops | H68: Crew Neck Tee | I68: 1199 | J68: 2 | K68: Valid Quantity | L68: 2398 | M68: 2398 | O68: 0 | P68: 0 | Q68: Wallet | R68: Website | S68: Noida | T68: Uttar Pradesh | U68: Delhi | V68: 45593 | W68: Valid Date | X68: On time delivery | Y68: Delivered | Z68: No | AC68: Not Returned | AD68: Not returned | AE68: Not Applicable
A69: UT-100073 | B69: 45583 | C69: Valid Q4 | D69: CUST_10072 | E69: New | F69: OUT-CDG-M | G69: Outerwear | H69: Cardigan | I69: 2599 | J69: 1 | K69: Valid Quantity | L69: 2599 | M69: 2079.2 | N69: DIWALI20 | O69: 20 | P69: 519.8 | Q69: Credit Card | R69: Instagram Shop | S69: Gurgaon | T69: Haryana | U69: Delhi | V69: 45595 | W69: Valid Date | X69: On time delivery | Y69: Delivered | Z69: Yes | AA69: Size Issue | AB69: 45622 | AC69: Returned | AD69: Valid | AE69: Processed
A70: UT-100074 | B70: 45583 | C70: Valid Q4 | D70: CUST_10073 | E70: Returning | F70: ACC-SCR-OS | G70: Accessories | H70: Hair Scrunchie | I70: 299 | J70: 5 | K70: Valid Quantity | L70: 1495 | M70: 1495 | O70: 0 | P70: 0 | Q70: UPI | R70: Mobile App | S70: Indore | T70: Madhya Pradesh | U70: Mumbai | V70: 45592 | W70: Valid Date | X70: On time delivery | Y70: Delivered | Z70: No | AC70: Not Returned | AD70: Not returned | AE70: Not Applicable
A71: UT-100075 | B71: 45583 | C71: Valid Q4 | D71: CUST_10074 | E71: New | F71: BOT-PPR-M | G71: Bottoms | H71: Paper Bag Pants | I71: 1899 | J71: 1 | K71: Valid Quantity | L71: 1899 | M71: 1899 | O71: 0 | P71: 0 | Q71: Debit Card | R71: Website | S71: Surat | T71: Gujarat | U71: Mumbai | V71: 45595 | W71: Valid Date | X71: On time delivery | Y71: Delivered | Z71: Yes | AA71: Wrong Item | AB71: 45624 | AC71: Returned | AD71: Valid | AE71: Processed
A72: UT-100076 | B72: 45584 | C72: Valid Q4 | D72: CUST_10075 | E72: New | F72: DRS-SMK-S | G72: Dresses | H72: Smocked Dress | I72: 2199 | J72: 1 | K72: Valid Quantity | L72: 2199 | M72: 2199 | O72: 0 | P72: 0 | Q72: Credit Card | R72: Instagram Shop | S72: Patna | T72: Bihar | U72: Delhi | V72: 45596 | W72: Valid Date | X72: On time delivery | Y72: Delivered | Z72: No | AC72: Not Returned | AD72: Not returned | AE72: Not Applicable
A73: UT-100077 | B73: 45584 | C73: Valid Q4 | D73: CUST_10076 | E73: New | F73: TOP-BTN-M | G73: Tops | H73: Button-Down Shirt | I73: 1799 | J73: 1 | K73: Valid Quantity | L73: 1799 | M73: 1619.1 | N73: FLAT10 | O73: 10 | P73: 179.9 | Q73: COD | R73: Mobile App | S73: Bhopal | T73: Madhya Pradesh | U73: Mumbai | V73: 45594 | W73: Valid Date | X73: On time delivery | Y73: Delivered | Z73: Yes | AA73: Quality Defect | AB73: 45621 | AC73: Returned | AD73: Valid | AE73: Processed
A74: UT-100078 | B74: 45584 | C74: Valid Q4 | D74: CUST_10077 | E74: Returning | F74: OUT-VLV-L | G74: Outerwear | H74: Velvet Blazer | I74: 4999 | J74: 1 | K74: Valid Quantity | L74: 4999 | M74: 4999 | O74: 0 | P74: 0 | Q74: UPI | R74: Website | S74: Nagpur | T74: Maharashtra | U74: Mumbai | V74: 45597 | W74: Valid Date | X74: On time delivery | Y74: Delivered | Z74: No | AC74: Not Returned | AD74: Not returned | AE74: Not Applicable
A75: UT-100079 | B75: 45584 | C75: Valid Q4 | D75: CUST_10078 | E75: New | F75: ACC-TOT-OS | G75: Accessories | H75: Canvas Tote | I75: 999 | J75: 1 | K75: Valid Quantity | L75: 999 | M75: 999 | O75: 0 | P75: 0 | Q75: Wallet | R75: Instagram Shop | S75: Coimbatore | T75: Tamil Nadu | U75: Bangalore | V75: 45595 | W75: Valid Date | X75: On time delivery | Y75: Delivered | Z75: Yes | AA75: Size Issue | AB75: 45624 | AC75: Returned | AD75: Valid | AE75: Processed
A76: UT-100080 | B76: 45585 | C76: Valid Q4 | D76: CUST_10079 | E76: New | F76: BOT-CRG-S | G76: Bottoms | H76: Cargo Shorts | I76: 1499 | J76: 1 | K76: Valid Quantity | L76: 1499 | M76: 1199.2 | N76: DIWALI20 | O76: 20 | P76: 299.8 | Q76: Credit Card | R76: Mobile App | S76: Kochi | T76: Kerala | U76: Bangalore | V76: 45596 | W76: Valid Date | X76: On time delivery | Y76: Delivered | Z76: No | AC76: Not Returned | AD76: Not returned | AE76: Not Applicable
A77: UT-100081 | B77: 45585 | C77: Valid Q4 | D77: CUST_10080 | E77: New | F77: DRS-BTR-M | G77: Dresses | H77: Butterfly Dress | I77: 2899 | J77: 1 | K77: Valid Quantity | L77: 2899 | M77: 2899 | O77: 0 | P77: 0 | Q77: Debit Card | R77: Website | S77: Vizag | T77: Andhra Pradesh | U77: Bangalore | V77: 45598 | W77: Valid Date | X77: On time delivery | Y77: Delivered | Z77: Yes | AA77: Changed Mind | AB77: 45626 | AC77: Returned | AD77: Valid | AE77: Processed
A78: UT-100082 | B78: 45585 | C78: Valid Q4 | D78: CUST_10081 | E78: Returning | F78: TOP-VNK-L | G78: Tops | H78: V-Neck Tee | I78: 1099 | J78: 2 | K78: Valid Quantity | L78: 2198 | M78: 2198 | O78: 0 | P78: 0 | Q78: UPI | R78: Instagram Shop | S78: Thiruvananthapuram | T78: Kerala | U78: Bangalore | V78: 45595 | W78: Valid Date | X78: On time delivery | Y78: Delivered | Z78: No | AC78: Not Returned | AD78: Not returned | AE78: Not Applicable
A79: UT-100083 | B79: 45585 | C79: Valid Q4 | D79: CUST_10082 | E79: New | F79: OUT-TRN-M | G79: Outerwear | H79: Trench Coat | I79: 5499 | J79: 1 | K79: Valid Quantity | L79: 5499 | M79: 4674.15 | N79: FIRST15 | O79: 15 | P79: 824.85 | Q79: Credit Card | R79: Mobile App | S79: Mysore | T79: Karnataka | U79: Bangalore | V79: 45599 | W79: Valid Date | X79: On time delivery | Y79: Delivered | Z79: Yes | AA79: Size Issue | AB79: 45627 | AC79: Returned | AD79: Valid | AE79: Processed
A80: UT-100084 | B80: 45586 | C80: Valid Q4 | D80: CUST_10083 | E80: New | F80: ACC-BDY-OS | G80: Accessories | H80: Body Chain | I80: 799 | J80: 1 | K80: Valid Quantity | L80: 799 | M80: 799 | O80: 0 | P80: 0 | Q80: COD | R80: Website | S80: Vadodara | T80: Gujarat | U80: Mumbai | W80: Not Delivered | X80: Not delivered | Y80: RTO | Z80: No | AC80: Not Delivered | AD80: Not returned | AE80: Not Applicable
A81: UT-100085 | B81: 45586 | C81: Valid Q4 | D81: CUST_10084 | E81: New | F81: BOT-JGR-L | G81: Bottoms | H81: Jogger Pants | I81: 1599 | J81: 1 | K81: Valid Quantity | L81: 1599 | M81: 1599 | O81: 0 | P81: 0 | Q81: Wallet | R81: Instagram Shop | S81: Rajkot | T81: Gujarat | U81: Mumbai | V81: 45598 | W81: Valid Date | X81: On time delivery | Y81: Delivered | Z81: No | AC81: Not Returned | AD81: Not returned | AE81: Not Applicable
A82: UT-100086 | B82: 45586 | C82: Valid Q4 | D82: CUST_10085 | E82: Returning | F82: DRS-RFL-S | G82: Dresses | H82: Ruffle Dress | I82: 2699 | J82: 1 | K82: Valid Quantity | L82: 2699 | M82: 2159.2 | N82: DIWALI20 | O82: 20 | P82: 539.8 | Q82: Credit Card | R82: Mobile App | S82: Kanpur | T82: Uttar Pradesh | U82: Delhi | V82: 45597 | W82: Valid Date | X82: On time delivery | Y82: Delivered | Z82: Yes | AA82: Quality Defect | AB82: 45626 | AC82: Returned | AD82: Valid | AE82: Processed
A83: UT-100087 | B83: 45586 | C83: Valid Q4 | D83: CUST_10086 | E83: New | F83: TOP-SQR-M | G83: Tops | H83: Square Neck Top | I83: 1499 | J83: 1 | K83: Valid Quantity | L83: 1499 | M83: 1499 | O83: 0 | P83: 0 | Q83: UPI | R83: Website | S83: Mumbai | T83: Maharashtra | U83: Mumbai | V83: 45598 | W83: Valid Date | X83: On time delivery | Y83: Delivered | Z83: No | AC83: Not Returned | AD83: Not returned | AE83: Not Applicable
A84: UT-100088 | B84: 45587 | C84: Valid Q4 | D84: CUST_10087 | E84: New | F84: OUT-WND-L | G84: Outerwear | H84: Windbreaker | I84: 3299 | J84: 1 | K84: Valid Quantity | L84: 3299 | M84: 3299 | O84: 0 | P84: 0 | Q84: Debit Card | R84: Instagram Shop | S84: Delhi | T84: Delhi | U84: Delhi | V84: 45600 | W84: Valid Date | X84: On time delivery | Y84: Delivered | Z84: Yes | AA84: Wrong Item | AB84: 45629 | AC84: Returned | AD84: Valid | AE84: Processed
A85: UT-100089 | B85: 45587 | C85: Valid Q4 | D85: CUST_10088 | E85: New | F85: ACC-ANK-OS | G85: Accessories | H85: Anklet | I85: 499 | J85: 2 | K85: Valid Quantity | L85: 998 | M85: 898.2 | N85: FLAT10 | O85: 10 | P85: 99.8 | Q85: Credit Card | R85: Mobile App | S85: Kolkata | T85: West Bengal | U85: Delhi | V85: 45597 | W85: Valid Date | X85: On time delivery | Y85: Delivered | Z85: No | AC85: Not Returned | AD85: Not returned | AE85: Not Applicable
A86: UT-100090 | B86: 45587 | C86: Valid Q4 | D86: CUST_10089 | E86: Returning | F86: BOT-TRS-M | G86: Bottoms | H86: Tailored Trousers | I86: 2399 | J86: 1 | K86: Valid Quantity | L86: 2399 | M86: 2399 | O86: 0 | P86: 0 | Q86: UPI | R86: Website | S86: Chennai | T86: Tamil Nadu | U86: Bangalore | V86: 45599 | W86: Valid Date | X86: On time delivery | Y86: Delivered | Z86: No | AC86: Not Returned | AD86: Not returned | AE86: Not Applicable
A87: UT-100091 | B87: 45587 | C87: Valid Q4 | D87: CUST_10090 | E87: New | F87: DRS-LST-M | G87: Dresses | H87: Lace Trim Dress | I87: 2599 | J87: 1 | K87: Valid Quantity | L87: 2599 | M87: 2599 | O87: 0 | P87: 0 | Q87: COD | R87: Instagram Shop | S87: Hyderabad | T87: Telangana | U87: Bangalore | W87: Not Delivered | X87: Not delivered | Y87: RTO | Z87: No | AC87: Not Delivered | AD87: Not returned | AE87: Not Applicable
A88: UT-100092 | B88: 45588 | C88: Valid Q4 | D88: CUST_10091 | E88: New | F88: TOP-TIE-S | G88: Tops | H88: Tie-Front Top | I88: 1399 | J88: 1 | K88: Valid Quantity | L88: 1399 | M88: 1119.2 | N88: DIWALI20 | O88: 20 | P88: 279.8 | Q88: Wallet | R88: Mobile App | S88: Pune | T88: Maharashtra | U88: Mumbai | V88: 45599 | W88: Valid Date | X88: On time delivery | Y88: Delivered | Z88: Yes | AA88: Size Issue | AB88: 45628 | AC88: Returned | AD88: Valid | AE88: Processed
A89: UT-100093 | B89: 45588 | C89: Valid Q4 | D89: CUST_10092 | E89: New | F89: OUT-PUF-M | G89: Outerwear | H89: Puffer Jacket | I89: 4299 | J89: 1 | K89: Valid Quantity | L89: 4299 | M89: 4299 | O89: 0 | P89: 0 | Q89: Credit Card | R89: Website | S89: Ahmedabad | T89: Gujarat | U89: Mumbai | V89: 45601 | W89: Valid Date | X89: On time delivery | Y89: Delivered | Z89: No | AC89: Not Returned | AD89: Not returned | AE89: Not Applicable
A90: UT-100094 | B90: 45588 | C90: Valid Q4 | D90: CUST_10093 | E90: Returning | F90: ACC-HDR-OS | G90: Accessories | H90: Hairband | I90: 399 | J90: 3 | K90: Valid Quantity | L90: 1197 | M90: 1197 | O90: 0 | P90: 0 | Q90: UPI | R90: Instagram Shop | S90: Jaipur | T90: Rajasthan | U90: Delhi | V90: 45598 | W90: Valid Date | X90: On time delivery | Y90: Delivered | Z90: No | AC90: Not Returned | AD90: Not returned | AE90: Not Applicable
A91: UT-100095 | B91: 45588 | C91: Valid Q4 | D91: CUST_10094 | E91: New | F91: BOT-PLT-L | G91: Bottoms | H91: Pleated Trousers | I91: 2199 | J91: 1 | K91: Valid Quantity | L91: 2199 | M91: 1869.15 | N91: FIRST15 | O91: 15 | P91: 329.85 | Q91: Debit Card | R91: Mobile App | S91: Lucknow | T91: Uttar Pradesh | U91: Delhi | V91: 45601 | W91: Valid Date | X91: On time delivery | Y91: Delivered | Z91: Yes | AA91: Damaged in Transit | AB91: 45631 | AC91: Returned | AD91: Valid | AE91: Processed
A92: UT-100096 | B92: 45589 | C92: Valid Q4 | D92: CUST_10095 | E92: New | F92: DRS-SHR-S | G92: Dresses | H92: Shirtdress | I92: 2399 | J92: 1 | K92: Valid Quantity | L92: 2399 | M92: 2399 | O92: 0 | P92: 0 | Q92: Credit Card | R92: Website | S92: Bangalore | T92: Karnataka | U92: Bangalore | V92: 45600 | W92: Valid Date | X92: On time delivery | Y92: Delivered | Z92: No | AC92: Not Returned | AD92: Not returned | AE92: Not Applicable
A93: UT-100097 | B93: 45589 | C93: Valid Q4 | D93: CUST_10096 | E93: New | F93: TOP-GRF-M | G93: Tops | H93: Graphic Tee | I93: 1299 | J93: 1 | K93: Valid Quantity | L93: 1299 | M93: 1299 | O93: 0 | P93: 0 | Q93: COD | R93: Instagram Shop | S93: Mumbai | T93: Maharashtra | U93: Mumbai | V93: 45602 | W93: Valid Date | X93: On time delivery | Y93: Delivered | Z93: Yes | AA93: Changed Mind | AB93: 45631 | AC93: Returned | AD93: Valid | AE93: Processed
A94: UT-100098 | B94: 45589 | C94: Valid Q4 | D94: CUST_10097 | E94: Returning | F94: OUT-SHW-L | G94: Outerwear | H94: Shawl Wrap | I94: 2799 | J94: 1 | K94: Valid Quantity | L94: 2799 | M94: 2239.2 | N94: DIWALI20 | O94: 20 | P94: 559.8 | Q94: UPI | R94: Mobile App | S94: Delhi | T94: Delhi | U94: Delhi | V94: 45601 | W94: Valid Date | X94: On time delivery | Y94: Delivered | Z94: No | AC94: Not Returned | AD94: Not returned | AE94: Not Applicable
A95: UT-100099 | B95: 45589 | C95: Valid Q4 | D95: CUST_10098 | E95: New | F95: ACC-BLT-S | G95: Accessories | H95: Braided Belt | I95: 699 | J95: 1 | K95: Valid Quantity | L95: 699 | M95: 699 | O95: 0 | P95: 0 | Q95: Wallet | R95: Website | S95: Chandigarh | T95: Punjab | U95: Delhi | V95: 45600 | W95: Valid Date | X95: On time delivery | Y95: Delivered | Z95: No | AC95: Not Returned | AD95: Not returned | AE95: Not Applicable
A96: UT-100100 | B96: 45590 | C96: Valid Q4 | D96: CUST_10099 | E96: New | F96: BOT-CUT-M | G96: Bottoms | H96: Culottes | I96: 1699 | J96: 1 | K96: Valid Quantity | L96: 1699 | M96: 1699 | O96: 0 | P96: 0 | Q96: Debit Card | R96: Instagram Shop | S96: Noida | T96: Uttar Pradesh | U96: Delhi | V96: 45603 | W96: Valid Date | X96: On time delivery | Y96: Delivered | Z96: Yes | AA96: Size Issue | AB96: 45632 | AC96: Returned | AD96: Valid | AE96: Processed
A97: UT-100101 | B97: 45590 | C97: Valid Q4 | D97: CUST_10100 | E97: New | F97: DRS-MXI-L | G97: Dresses | H97: Maxi Dress | I97: 2799 | J97: 1 | K97: Valid Quantity | L97: 2799 | M97: 2519.1 | N97: FLAT10 | O97: 10 | P97: 279.9 | Q97: Credit Card | R97: Mobile App | S97: Gurgaon | T97: Haryana | U97: Delhi | V97: 45602 | W97: Valid Date | X97: On time delivery | Y97: Delivered | Z97: No | AC97: Not Returned | AD97: Not returned | AE97: Not Applicable
A98: UT-100102 | B98: 45590 | C98: Valid Q4 | D98: CUST_10101 | E98: Returning | F98: TOP-SLV-S | G98: Tops | H98: Sleeveless Top | I98: 1199 | J98: 2 | K98: Valid Quantity | L98: 2398 | M98: 2398 | O98: 0 | P98: 0 | Q98: UPI | R98: Website | S98: Indore | T98: Madhya Pradesh | U98: Mumbai | V98: 45601 | W98: Valid Date | X98: On time delivery | Y98: Delivered | Z98: Yes | AA98: Quality Defect | AB98: 45630 | AC98: Returned | AD98: Valid | AE98: Processed
A99: UT-100103 | B99: 45590 | C99: Valid Q4 | D99: CUST_10102 | E99: New | F99: OUT-CPE-M | G99: Outerwear | H99: Cape Coat | I99: 5999 | J99: 1 | K99: Valid Quantity | L99: 5999 | M99: 5999 | O99: 0 | P99: 0 | Q99: Credit Card | R99: Instagram Shop | S99: Surat | T99: Gujarat | U99: Mumbai | V99: 45604 | W99: Valid Date | X99: On time delivery | Y99: Delivered | Z99: No | AC99: Not Returned | AD99: Not returned | AE99: Not Applicable
A100: UT-100104 | B100: 45591 | C100: Valid Q4 | D100: CUST_10103 | E100: New | F100: ACC-SHD-OS | G100: Accessories | H100: Shoulder Bag | I100: 1799 | J100: 1 | K100: Valid Quantity | L100: 1799 | M100: 1439.2 | N100: DIWALI20 | O100: 20 | P100: 359.8 | Q100: COD | R100: Mobile App | S100: Patna | T100: Bihar | U100: Delhi | W100: Not Delivered | X100: Not delivered | Y100: RTO | Z100: No | AC100: Not Delivered | AD100: Not returned | AE100: Not Applicable
...

Sheet Note
M1: Column | N1: Description
M2: discount_code | N2: Promo code applied; blank if no discount
M3: delivery_date | N3: Actual delivery date (blank if not delivered or cancelled)
M13: SKU - Stock keeping unit
M14: Totla_order - unit_price × quantity
M15: AOV - Average Order Value
M16: RTO - Return To Origin

Sheet Q4_Summary_Dashboard
C4: Row Labels | D4: Total Order | E4: Totla Revenue (After discount) | F4: Total Units Sold | H4: AOV (avergae order value) | I4: Overall Return Rate %
C5: 01-10-2024 - 07-10-2024 | D5: 26 | E5: 72576.7 | F5: 40 | H5: =GETPIVOTDATA("Totla Revenue (After discount)",Q4_Summary_Dashboard!$C$4)/GETPIVOTDATA("Total Order",Q4_Summary_Dashboard!$C$4) -> 2626.0087 | I5: =(I14/I15)*100 -> 55.140187
C6: 08-10-2024 - 14-10-2024 | D6: 29 | E6: 73463.65 | F6: 33
C7: 15-10-2024 - 21-10-2024 | D7: 28 | E7: 57126.6 | F7: 35
C8: 22-10-2024 - 28-10-2024 | D8: 28 | E8: 61419.8 | F8: 34
C9: 29-10-2024 - 04-11-2024 | D9: 31 | E9: 71500.2 | F9: 33
C10: 05-11-2024 - 11-11-2024 | D10: 21 | E10: 46956.55 | F10: 27
C11: 12-11-2024 - 18-11-2024 | D11: 21 | E11: 62884.05 | F11: 22
C12: 19-11-2024 - 25-11-2024 | D12: 21 | E12: 57673.75 | F12: 22
C13: 26-11-2024 - 02-12-2024 | D13: 23 | E13: 64174.65 | F13: 27 | H13: AOV= sum(total revenue)/count(total order)
C14: 03-12-2024 - 09-12-2024 | D14: 27 | E14: 78752.6 | F14: 30 | H14: Return Initiated = | I14: =COUNTIFS(Cleaned_Data!Z:Z,"Yes") -> 177
C15: 10-12-2024 - 16-12-2024 | D15: 29 | E15: 86449.2 | F15: 33 | H15: Delivered Orders = | I15: =COUNTIF(Cleaned_Data!Y:Y,"Delivered") -> 321
C16: 17-12-2024 - 23-12-2024 | D16: 28 | E16: 82070 | F16: 32
C17: 24-12-2024 - 30-12-2024 | D17: 26 | E17: 71570 | F17: 32
C18: 31-12-2024 - 01-01-2025 | D18: 1 | E18: 3599.2 | F18: 1
C19: 45657 | D19: 1 | E19: 3599.2 | F19: 1
C20: Grand Total | D20: 339 | E20: 890216.95 | F20: 401

Sheet Trend Analysis
A1: Row Labels | B1: Order Volume | C1: Return Rate | D1: Average Discount %
A2: 01-10-2024 - 07-10-2024 | B2: 26 | C2: 10 | D2: 5.3846154
A3: 08-10-2024 - 14-10-2024 | B3: 29 | C3: 12 | D3: 5
A4: 15-10-2024 - 21-10-2024 | B4: 28 | C4: 12 | D4: 5.3571429
A5: 22-10-2024 - 28-10-2024 | B5: 28 | C5: 12 | D5: 11.785714
A6: 29-10-2024 - 04-11-2024 | B6: 31 | C6: 23 | D6: 40
A7: 05-11-2024 - 11-11-2024 | B7: 21 | C7: 11 | D7: 11.190476
A8: 12-11-2024 - 18-11-2024 | B8: 21 | C8: 12 | D8: 4.2857143
A9: 19-11-2024 - 25-11-2024 | B9: 21 | C9: 11 | D9: 3.5714286
A10: 26-11-2024 - 02-12-2024 | B10: 23 | C10: 12 | D10: 6.3043478
A11: 03-12-2024 - 09-12-2024 | B11: 27 | C11: 12 | D11: 8.1481481
A12: 10-12-2024 - 16-12-2024 | B12: 29 | C12: 16 | D12: 6.8965517
A13: 17-12-2024 - 23-12-2024 | B13: 28 | C13: 17 | D13: 6.4285714
... A16: Grand Total | B16: 339 | C16: 177 | D16: 9.8230088

Sheet Segment Analysis
A1: Row Labels | B1: Order Volume | C1: Average Order Value | D1: Return Count | E1: Return Rate
A2: New | B2: 264 | C2: 2599.9544 | D2: 145 | E2: =GETPIVOTDATA("Return Count",$A$1,"Type","New")/GETPIVOTDATA("Order Volume",$A$1,"Type","New")*100 -> 54.924242
A3: Returning | B3: 75 | C3: 2717.72 | D3: 32 | E3: =GETPIVOTDATA("Return Count",$A$1,"Type","Returning")/GETPIVOTDATA("Order Volume",$A$1,"Type","Returning")*100 -> 42.666667
A4: Grand Total | B4: 339 | C4: 2626.0087 | D4: 177
A7: Row Labels | B7: Count of Order ID | C7: Average of Order_Total_After_Discount | D7: Count of Return Received | E7: Return Rate
A8: Instagram Shop | B8: 108 | C8: 2757.1625 | D8: 70 | E8: =GETPIVOTDATA("Count of Return Received",$A$7,"Source","Instagram Shop")/GETPIVOTDATA("Count of Order ID",$A$7,"Source","Instagram Shop")*100 -> 64.814815
A9: Mobile App | B9: 114 | C9: 2552.3408 | D9: 59 | E9: =GETPIVOTDATA("Count of Return Received",$A$7,"Source","Mobile App")/GETPIVOTDATA("Count of Order ID",$A$7,"Source","Mobile App")*100 -> 51.754386
A10: Website | B10: 117 | C10: 2576.7226 | D10: 48 | E10: =GETPIVOTDATA("Count of Return Received",$A$7,"Source","Website")/GETPIVOTDATA("Count of Order ID",$A$7,"Source","Website")*100 -> 41.025641
A11: Grand Total | B11: 339 | C11: 2626.0087 | D11: 177
A14: Row Labels | B14: Count of Order ID | C14: Average of Order_Total_After_Discount | D14: Count of Return Received | E14: Return Rate
A15: COD | B15: 62 | C15: 3033.2798 | D15: 38 | E15: =GETPIVOTDATA("Count of Return Received",$A$14,"Payment","COD")/GETPIVOTDATA("Count of Order ID",$A$14,"Payment","COD")*100 -> 61.290323
A16: Credit Card | B16: 86 | C16: 3107.2041 | D16: 46 | E16: =GETPIVOTDATA("Count of Return Received",$A$14,"Payment","Credit Card")/GETPIVOTDATA("Count of Order ID",$A$14,"Payment","Credit Card")*100 -> 53.488372
A17: Debit Card | B17: 59 | C17: 2473.3483 | D17: 42 | E17: =GETPIVOTDATA("Count of Return Received",$A$14,"Payment","Debit Card")/GETPIVOTDATA("Count of Order ID",$A$14,"Payment","Debit Card")*100 -> 71.186441
A18: UPI | B18: 80 | C18: 2327.78 | D18: 35 | E18: =GETPIVOTDATA("Count of Return Received",$A$14,"Payment","UPI")/GETPIVOTDATA("Count of Order ID",$A$14,"Payment","UPI")*100 -> 43.75
A19: Wallet | B19: 52 | C19: 1976.6173 | D19: 16 | E19: =GETPIVOTDATA("Count of Return Received",$A$14,"Payment","Wallet")/GETPIVOTDATA("Count of Order ID",$A$14,"Payment","Wallet")*100 -> 30.769231
A20: Grand Total | B20: 339 | C20: 2626.0087 | D20: 177
A23: Row Labels | B23: Count of Order ID | C23: Average of Order_Total_After_Discount | D23: Count of Return Received | E23: Return Rate
A24: Accessories | B24: 67 | C24: 1275.8328 | D24: 16 | E24: =GETPIVOTDATA("Count of Return Received",$A$23,"Category","Accessories")/GETPIVOTDATA("Count of Order ID",$A$23,"Category","Accessories")*100 -> 23.880597
A25: Bottoms | B25: 66 | C25: 2073.1129 | D25: 25 | E25: =GETPIVOTDATA("Count of Return Received",$A$23,"Category","Bottoms")/GETPIVOTDATA("Count of Order ID",$A$23,"Category","Bottoms")*100 -> 37.878788
A26: Dresses | B26: 68 | C26: 3144.4037 | D26: 42 | E26: =GETPIVOTDATA("Count of Return Received",$A$23,"Category","Dresses")/GETPIVOTDATA("Count of Order ID",$A$23,"Category","Dresses")*100 -> 61.764706
A27: Outerwear | B27: 67 | C27: 4682.6918 | D27: 51 | E27: =GETPIVOTDATA("Count of Return Received",$A$23,"Category","Outerwear")/GETPIVOTDATA("Count of Order ID",$A$23,"Category","Outerwear")*100 -> 76.119403
A28: Tops | B28: 71 | C28: 1976.7732 | D28: 43 | E28: =GETPIVOTDATA("Count of Return Received",$A$23,"Category","Tops")/GETPIVOTDATA("Count of Order ID",$A$23,"Category","Tops")*100 -> 60.56338
A29: Grand Total | B29: 339 | C29: 2626.0087 | D29: 177

Sheet KPI Metrics
C3: GMV= | D3: =SUM(Table1_12[Total]) -> 1003499 | H3: count(RTO)= | I3: =COUNTIF(Table1_12[Status],"rto") -> 17
C4: Net revenue= | D4: =SUM(Table1_12[Order_Total_After_Discount]) -> 890216.95 | H4: count(Delivery date)= | I4: =COUNT(Table1_12[Delivery Date]) -> 321
C5: Return Rate= | D5: =(COUNT(Table1_12[Return Received])/(COUNT(Table1_12[Delivery Date])))*100 -> 55.140187
C6: RTO Rate= | D6: =I3/I4*100 -> 5.2959502
C7: Refund Processing Rate = | D7: =COUNTIF(Table1_12[Refund],"processed")/COUNT(Cleaned_Data!AB:AB)*100 -> 96.610169 | H7: Row Labels | I7: Order Volume | J7: Average Order Value | K7: Return Count
C8: First Time Buyer Return Rate = | D8: =GETPIVOTDATA("Return Count",$H$7,"Type","New")/GETPIVOTDATA("Order Volume",$H$7,"Type","New")*100 -> 54.924242 | H8: New | I8: 264 | J8: 2599.9544 | K8: 145
C9: Returning Time Buyer Return Rate = | D9: =GETPIVOTDATA("Return Count",$H$7,"Type","Returning")/GETPIVOTDATA("Order Volume",$H$7,"Type","Returning")*100 -> 42.666667 | H9: Returning | I9: 75 | J9: 2717.72 | K9: 32
C10: Bangalore fullfillment = | D10: =I12/I15*100 -> 27.138643 | H10: Grand Total | I10: 339 | J10: 2626.0087 | K10: 177
C11: Delhi fullfillment= | D11: =I13/I15*100 -> 37.758112
C12: Mumbai fullfillment= | D12: =I14/I15*100 -> 35.103245 | H12: Bangalore warehouse = | I12: =COUNTIF(Cleaned_Data!U:U,"bangalore") -> 92
H13: delhi warehouse = | I13: =COUNTIF(Cleaned_Data!U:U,"delhi") -> 128
H14: mumbai warehouse = | I14: =COUNTIF(Cleaned_Data!U:U,"mumbai") -> 119
I15: =SUM(I12:I14) -> 339

Sheet Business Interpretation

Sheet Cleaning_Log

Sheet Validation Summary

Sheet Analysis
